{
  "PrivateVPNs": {
    "last_updated": "2025-08-14T14:20:13.719500",
    "file_hash": "842b29f3bfacd5772488d4a75c46c965"
  },
  "V2rayNG3": {
    "last_updated": "2025-08-07T18:23:48.248052",
    "file_hash": "6a56d722f4635a4689784f656a513946"
  },
  "V2rayNGX": {
    "last_updated": "2025-08-07T12:31:42.787834",
    "file_hash": "6566eb6d6814667b061b4700332f70f4"
  },
  "V2rayNGzendegimamad": {
    "last_updated": "2025-08-07T01:10:13.356198",
    "file_hash": "b9d2d4a8869981bc05bd4be186728231"
  },
  "V2pedia": {
    "last_updated": "2025-08-14T20:27:17.949126",
    "file_hash": "201856c09b856434d0917468992f9f64"
  },
  "V2rayprotocol": {
    "last_updated": "2025-08-07T18:23:48.248052",
    "file_hash": "f489ab1c7cf42af4a9dc6ef17f8ba356"
  },
  "V2raythekyo": {
    "last_updated": "2025-08-14T20:27:17.949126",
    "file_hash": "7f148f6c5b1524dcd0282887cf34f472"
  },
  "V2rex": {
    "last_updated": "2025-08-07T06:24:45.975540",
    "file_hash": "827cdc37315a70d4948f63cf26f32fad"
  },
  "V2ry_proxy": {
    "last_updated": "2025-08-07T01:10:13.356198",
    "file_hash": "86b04e2639a35ae2f06e67e5c447b79a"
  },
  "V2source": {
    "last_updated": "2025-08-07T01:10:13.356198",
    "file_hash": "3ad131259186b85165e4cda722e4cde9"
  },
  "ViPVpn_v2ray": {
    "last_updated": "2025-08-06T12:31:31.275312",
    "file_hash": "900628c90eb8033dff95edcf6092ccfb"
  },
  "VmessProtocol": {
    "last_updated": "2025-08-07T01:10:13.356198",
    "file_hash": "edab8042933959faa2c6a70a654af2f6"
  },
  "VlessConfig": {
    "last_updated": "2025-08-07T18:23:48.248052",
    "file_hash": "e929ff3bc0f71e0dce934b2efbb0e4f6"
  },
  "ae_proxy": {
    "last_updated": "2025-07-22T18:19:48.190890",
    "file_hash": "e83eeb187a16c5f6ea91b19d8c637fca"
  },
  "alfa_v2ray_ng": {
    "last_updated": "2025-08-07T01:10:13.356198",
    "file_hash": "c20eebeee08cf790922ae8bc49052aa7"
  },
  "alfred_config": {
    "last_updated": "2025-07-22T18:19:48.190890",
    "file_hash": "3f823100314a29121019c025840899b9"
  },
  "alo_v2rayng": {
    "last_updated": "2025-08-07T18:23:48.248052",
    "file_hash": "3ac2bd6a73badb0f99b763b263530fd0"
  },
  "amirw_shop_q": {
    "last_updated": "2025-08-07T18:23:48.248052",
    "file_hash": "90854f30e29d2be8a34b317e539abed3"
  },
  "anty_vpn": {
    "last_updated": "2025-08-04T06:50:54.999386",
    "file_hash": "4e173efd96c7849f9588c952c145b971"
  },
  "appsooner": {
    "last_updated": "2025-08-07T12:31:42.787834",
    "file_hash": "b0d214ae2bcb6f634142957052cde112"
  },
  "artemis_vpn_free": {
    "last_updated": "2025-08-07T12:31:42.787834",
    "file_hash": "bf5fdd0796c1e6a8a93ebac6ebbc3803"
  },
  "arv2ra": {
    "last_updated": "2025-08-14T20:27:17.949126",
    "file_hash": "39aeb33d2077807b7825d16c69d206af"
  },
  "arv2ray": {
    "last_updated": "2025-08-14T20:27:17.949126",
    "file_hash": "cebeb498cdef2f3a1e758448b201f52e"
  },
  "ata_connect": {
    "last_updated": "2025-08-07T12:31:42.787834",
    "file_hash": "908ecbc9b996be24f326c7f8792fd2a1"
  },
  "awlix_ir": {
    "last_updated": "2025-08-07T06:24:45.975540",
    "file_hash": "d7a019ecb69535a7269936307b2303ba"
  },
  "aymh19": {
    "last_updated": "2025-08-07T12:31:42.787834",
    "file_hash": "2da7bdd0b8734c6d330a71d6a9cc6dcf"
  },
  "azad_intrnet": {
    "last_updated": "2025-08-06T18:22:58.666536",
    "file_hash": "ff900bcc016c6fd3eed1807d944ff96f"
  },
  "azadiiivpn": {
    "last_updated": "2025-08-06T18:22:58.666536",
    "file_hash": "15b6c7c7aacc48541ae182093a866b43"
  },
  "azadnett1": {
    "last_updated": "2025-08-06T18:22:58.666536",
    "file_hash": "3266c72b4bd55579fc46db145269ca9f"
  },
  "azarbayjab1": {
    "last_updated": "2025-07-22T18:19:48.190890",
    "file_hash": "864ffecde66a407cdbbea9da1af843ba"
  },
  "banv2ray": {
    "last_updated": "2025-07-22T18:19:48.190890",
    "file_hash": "80a241e19812ce08a611b4c026ffbc09"
  },
  "baraye_azadi_info": {
    "last_updated": "2025-08-06T18:22:58.666536",
    "file_hash": "3843aa4de943f17108d0b5830fe75ed7"
  },
  "befreewithus": {
    "last_updated": "2025-07-22T18:19:48.190890",
    "file_hash": "1af1160bf672c4fa2ebefc45e48117f6"
  },
  "berice_v2": {
    "last_updated": "2025-08-14T20:27:17.949126",
    "file_hash": "99fbc1f0b6840be32608eaff104320c2"
  },
  "bimnetvpn": {
    "last_updated": "2025-08-07T01:10:13.356198",
    "file_hash": "d71c4c2255c0917322c6e2258089c109"
  },
  "bypass_filter": {
    "last_updated": "2025-07-22T18:19:48.190890",
    "file_hash": "cf86c8683c3de0927e96ea2364c16ae2"
  },
  "castom_v2ray": {
    "last_updated": "2025-08-14T20:27:17.949126",
    "file_hash": "a1e34e58226a876bb68a4b36a234bcba"
  },
  "configV2rayForFree": {
    "last_updated": "2025-08-06T12:31:31.275312",
    "file_hash": "f4fa67211872f86686583ba8da8a5df2"
  },
  "config_green": {
    "last_updated": "2025-08-06T12:31:31.275312",
    "file_hash": "3e2d77ff36e6ba896e88a879cead6cb0"
  },
  "configasli": {
    "last_updated": "2025-08-06T18:22:58.666536",
    "file_hash": "2e6e0c37ea9bd34d6317913749a4337e"
  },
  "configforvpn": {
    "last_updated": "2025-07-22T18:19:48.190890",
    "file_hash": "92fb182f59be528e77a94b3e9e512e94"
  },
  "configfree_1": {
    "last_updated": "2025-08-14T20:27:17.949126",
    "file_hash": "b2326c1726f0f84f0163bfa715dae95a"
  },
  "configms": {
    "last_updated": "2025-07-22T18:19:48.190890",
    "file_hash": "d1ee13e8d5ce5ff4713df4455c5c8a7c"
  },
  "configrayegan": {
    "last_updated": "2025-08-07T12:31:42.787834",
    "file_hash": "9d2183d96d2c7e84c5f15158b53e94bf"
  },
  "configv2rayngvpn": {
    "last_updated": "2025-08-04T06:50:54.999386",
    "file_hash": "6b753a94cff167e9f9073ee6e6af85c9"
  },
  "configx2ray": {
    "last_updated": "2025-08-07T01:10:13.356198",
    "file_hash": "bc686767504ddcc10bf3f4fa5ce3e2b0"
  },
  "confing_chanel": {
    "last_updated": "2025-08-05T12:31:44.499348",
    "file_hash": "9193b3b28f9dbda46c7f750a8ec664d4"
  },
  "connectbemon": {
    "last_updated": "2025-08-07T18:23:48.248052",
    "file_hash": "69f6cf5e4410d30a9f0978f4016a3efa"
  },
  "custom_14": {
    "last_updated": "2025-08-04T06:50:54.999386",
    "file_hash": "0eeec219644b5d17f3708fdd37965652"
  },
  "customizev2ray": {
    "last_updated": "2025-08-04T06:50:54.999386",
    "file_hash": "6a830ebcb30004007e31085291668ac5"
  },
  "customvpnserver": {
    "last_updated": "2025-08-14T20:27:17.949126",
    "file_hash": "4fe0ec54e942095b85ef660e803111e3"
  },
  "darkline_vpn": {
    "last_updated": "2025-07-22T18:19:48.190890",
    "file_hash": "8084f872c8ff64246c3306b382338330"
  },
  "diamondproxytm": {
    "last_updated": "2025-07-22T18:19:48.190890",
    "file_hash": "ed8152c5a9dbcb646506a8f10b00ab7a"
  },
  "digiv2ray": {
    "last_updated": "2025-08-07T18:23:48.248052",
    "file_hash": "bf5a653bd241fb9f9d96eb8b6afc34fe"
  },
  "directvpn": {
    "last_updated": "2025-08-14T20:27:17.949126",
    "file_hash": "94e815953035e69fb3c2eddeb9aa3372"
  },
  "do_itforyou": {
    "last_updated": "2025-08-07T12:31:42.787834",
    "file_hash": "8e09f2e413e96498387196e6797b877c"
  },
  "dr_v2ray": {
    "last_updated": "2025-08-07T12:31:42.787834",
    "file_hash": "c9b55d4b49acc6b7b8cbd3f37fac7bf9"
  },
  "drakvpn": {
    "last_updated": "2025-08-14T20:27:17.949126",
    "file_hash": "10ea34eaf23b65df5888b2349a962193"
  },
  "empirevpn7": {
    "last_updated": "2025-08-14T20:27:17.949126",
    "file_hash": "c6009d5bfc9a88717c59fc8b4c1f0770"
  },
  "entrynet": {
    "last_updated": "2025-08-07T18:23:48.248052",
    "file_hash": "82309cd8f644768ca4214d0589129a3d"
  },
  "ev2rayy": {
    "last_updated": "2025-08-07T06:24:45.975540",
    "file_hash": "3038ba364f5f0acf80eb731331657dd9"
  },
  "evay_vpn": {
    "last_updated": "2025-08-07T12:31:42.787834",
    "file_hash": "ccc81f56724d80a8dd94fc28278b9018"
  },
  "expressvpn_420": {
    "last_updated": "2025-08-07T06:24:45.975540",
    "file_hash": "bff2e3d8de75909f59fa2f6bf8fd5c7d"
  },
  "farah_vpn": {
    "last_updated": "2025-08-07T01:10:13.356198",
    "file_hash": "5a52e40e1222f5edd084d6a5c8b7dbea"
  },
  "farahvpn": {
    "last_updated": "2025-08-14T20:27:17.949126",
    "file_hash": "0c3582b75eb21e117cb3839e74c17ee4"
  },
  "fast_2ray": {
    "last_updated": "2025-08-07T18:23:48.248052",
    "file_hash": "7618aa1fba73319d039f4cc3a295e4ad"
  },
  "fastshovpn": {
    "last_updated": "2025-08-07T12:31:42.787834",
    "file_hash": "31d901eb9b358b0e4558deb428865894"
  },
  "fhkllvjkll": {
    "last_updated": "2025-08-14T20:27:17.949126",
    "file_hash": "e401ff138499eed2a7b95a09cd7ff97e"
  },
  "filter_breaker": {
    "last_updated": "2025-07-22T18:19:48.190890",
    "file_hash": "c7b2ed4b3624c9eb1dafa1e2c398197f"
  },
  "filterk0sh": {
    "last_updated": "2025-08-04T06:50:54.999386",
    "file_hash": "d26a052dbdb3d06d877045cd5e1f2e88"
  },
  "filtershekan_channel": {
    "last_updated": "2025-08-07T01:10:13.356198",
    "file_hash": "99df99b6ca03eb125bcd8729743b82ed"
  },
  "foxnt": {
    "last_updated": "2025-08-07T06:24:45.975540",
    "file_hash": "8b4c470dd948cfc471768a89a8fd363e"
  },
  "free4allVPN": {
    "last_updated": "2025-07-22T18:19:48.190890",
    "file_hash": "2db451048ad4ac436a556f20fd785830"
  },
  "free_outline_keys": {
    "last_updated": "2025-08-07T18:23:48.248052",
    "file_hash": "a3c0d7fecaa98905094776d385a260e9"
  },
  "freenapsternetv": {
    "last_updated": "2025-08-07T01:10:13.356198",
    "file_hash": "014512cd758e315cfe3a10cd62a0b104"
  },
  "freev2raym": {
    "last_updated": "2025-08-07T01:10:13.356198",
    "file_hash": "6afe9c55bf5d424467ad3aa82a994645"
  },
  "freevirgoolnet": {
    "last_updated": "2025-08-07T12:31:42.787834",
    "file_hash": "714325486354fd62c2ba78c11d77f8b7"
  },
  "g0dv2ray": {
    "last_updated": "2025-08-04T06:50:54.999386",
    "file_hash": "435e172d5496edce82c414a1905af29e"
  },
  "garnet_free": {
    "last_updated": "2025-07-22T18:19:48.190890",
    "file_hash": "ddea113e70bc20529f2681e3cf8f0b77"
  },
  "gh_v2rayng": {
    "last_updated": "2025-08-04T06:50:54.999386",
    "file_hash": "70d606d5c78ea51ba868e4a7bc88fd81"
  },
  "ghalagyann2": {
    "last_updated": "2025-08-04T12:31:40.411501",
    "file_hash": "5da58c57d322865583f828a4954a1f12"
  },
  "gozargah_azadi": {
    "last_updated": "2025-08-13T20:26:31.901431",
    "file_hash": "ce1460e4e95d4af4772a80f6c344c305"
  },
  "gozargahvpn": {
    "last_updated": "2025-08-07T01:10:13.356198",
    "file_hash": "cfcb4d408ee4f57d542b89a2848db906"
  },
  "hatunnel_vpn": {
    "last_updated": "2025-08-04T06:50:54.999386",
    "file_hash": "900a3df6b071bc8920acffbafd5337c1"
  },
  "hibyevpnn": {
    "last_updated": "2025-08-07T12:31:42.787834",
    "file_hash": "1766edde389a150f24e9b73cb566ba34"
  },
  "hiddify_nexttt": {
    "last_updated": "2025-08-06T01:09:59.624461",
    "file_hash": "e0fd4fdeb601460f18587b60366c173f"
  },
  "hope_net": {
    "last_updated": "2025-08-07T18:23:48.248052",
    "file_hash": "08a35d997a9c81fe8447488c1c52dc95"
  },
  "hopev2ray": {
    "last_updated": "2025-08-14T09:02:42.969926",
    "file_hash": "39d02e9c838e701422975eb3ca5cb6fc"
  },
  "http_injector99": {
    "last_updated": "2025-08-14T20:27:17.949126",
    "file_hash": "c6aa837d94adf797afa8e2f3f9f73d12"
  },
  "icloudyshop": {
    "last_updated": "2025-08-07T06:24:45.975540",
    "file_hash": "1888843d4d1ebb81c5967d1b0ff4ce69"
  },
  "icv2ray": {
    "last_updated": "2025-08-07T12:31:42.787834",
    "file_hash": "6d686a2cd74d2188c09c1b5334a94588"
  },
  "inikotesla": {
    "last_updated": "2025-08-14T20:27:17.949126",
    "file_hash": "ec6838686e084520d4191275da3a7a03"
  },
  "injastvpn": {
    "last_updated": "2025-08-07T18:23:48.248052",
    "file_hash": "5bf1c41707d7f6ccb6d809fb57a08034"
  },
  "ios_v2": {
    "last_updated": "2025-08-07T01:10:13.356198",
    "file_hash": "9ee3690c77d4835b90a232db899ef37e"
  },
  "ip_cf_config": {
    "last_updated": "2025-07-22T18:19:48.190890",
    "file_hash": "657f9056f89adf2126a8cf61132cd68c"
  },
  "ipv2ray": {
    "last_updated": "2025-07-19T09:32:23.143788",
    "file_hash": "ba4e103d242e55a715e06c65e5c296ee"
  },
  "ipv2rayng": {
    "last_updated": "2025-08-07T12:31:42.787834",
    "file_hash": "e1aa07a5d908d5690da0f458a43a03e7"
  },
  "iraniv2ray_config": {
    "last_updated": "2025-08-06T01:09:59.624461",
    "file_hash": "6ad5eb5c286009d255c64193ff6d1109"
  },
  "iranvpnet": {
    "last_updated": "2025-07-22T18:19:48.190890",
    "file_hash": "9ea25eeb17ecc44c8698d94e5aa58fe2"
  },
  "iranvpnnet": {
    "last_updated": "2025-08-14T20:27:17.949126",
    "file_hash": "bb38d4376285a1430c9ad86744af8dbf"
  },
  "irlast": {
    "last_updated": "2025-08-07T06:24:45.975540",
    "file_hash": "59ef55938f6b9df95bb3f19945da08ca"
  },
  "itenvpn": {
    "last_updated": "2025-08-06T18:22:58.666536",
    "file_hash": "fa5f7c461314177f5723c155ed1b001b"
  },
  "kafing_2": {
    "last_updated": "2025-08-06T18:22:58.666536",
    "file_hash": "af8f97f9917320f1ce0aa97acc904615"
  },
  "karingvpn": {
    "last_updated": "2025-08-06T06:25:33.942702",
    "file_hash": "23d8c01b670347859d877339e4f9b27d"
  },
  "kilid_stor": {
    "last_updated": "2025-08-07T01:10:13.356198",
    "file_hash": "6dfdfc9c08d57f126d9c3a34fbfdeb77"
  },
  "king_v2raay": {
    "last_updated": "2025-08-07T12:31:42.787834",
    "file_hash": "7b5868e784dc72f6aa3e2600239618c7"
  },
  "kurd_v2ray": {
    "last_updated": "2025-07-22T18:19:48.190890",
    "file_hash": "faaa94059bfaeb673c0710dd80ea0b7c"
  },
  "kurdvpn1": {
    "last_updated": "2025-08-05T12:31:44.499348",
    "file_hash": "f47cb7ba4d40144031e277a0f1a106ac"
  },
  "lexernet": {
    "last_updated": "2025-08-07T06:24:45.975540",
    "file_hash": "4a52fc516482b9961e15b4b7e5614208"
  },
  "lightningvpn_org": {
    "last_updated": "2025-08-07T01:10:13.356198",
    "file_hash": "d3ce03a18a855214c87866089a2c73bb"
  },
  "lockey_vpn": {
    "last_updated": "2025-07-22T18:19:48.190890",
    "file_hash": "2b89d1cb8b64d68f786c9fe9bf109e6a"
  },
  "luckyvpn": {
    "last_updated": "2025-08-07T01:10:13.356198",
    "file_hash": "1a7eaa36e5aff863f421582d246ff533"
  },
  "mahanvpn": {
    "last_updated": "2025-08-07T06:24:45.975540",
    "file_hash": "73246490b576dabdfa1c1994d607ab86"
  },
  "mahdi2000_m": {
    "last_updated": "2025-08-07T06:24:45.975540",
    "file_hash": "d0d2d1544e015069d6fc3f30b2bbb017"
  },
  "manzariyeh_rasht": {
    "last_updated": "2025-08-06T01:09:59.624461",
    "file_hash": "c9e5588f0fe940bbca1d3fbe9ea8f223"
  },
  "masterserver1": {
    "last_updated": "2025-08-07T12:31:42.787834",
    "file_hash": "b0eaa756c0a519b390c51c4f50abf1c7"
  },
  "meli_v2rayng": {
    "last_updated": "2025-07-22T18:19:48.190890",
    "file_hash": "d7532f7a131d02a8a955cef5322096c1"
  },
  "melliwnet": {
    "last_updated": "2025-08-06T06:25:33.942702",
    "file_hash": "6af3b0e97fef0d531d11a5dd028f8060"
  },
  "melov2ray": {
    "last_updated": "2025-08-07T06:24:45.975540",
    "file_hash": "9744dc268e5917f8d87f06d46910559f"
  },
  "mester_v2ray": {
    "last_updated": "2025-08-06T18:22:58.666536",
    "file_hash": "e4fabb66a851fed1b2d991222d840c13"
  },
  "moneyseae": {
    "last_updated": "2025-08-06T01:09:59.624461",
    "file_hash": "a47a62e5518dcc3186f06811dd3e2395"
  },
  "msv2flyng": {
    "last_updated": "2025-08-06T01:09:59.624461",
    "file_hash": "f14943be0dc77472f39f00a9cb611418"
  },
  "mux_vpn": {
    "last_updated": "2025-07-22T18:19:48.190890",
    "file_hash": "cc47236befa03e5e6e4913f9d471f3ab"
  },
  "n2vpn": {
    "last_updated": "2025-08-07T12:31:42.787834",
    "file_hash": "6c8ff5849bfb38fbfc8e19770892a8be"
  },
  "namiranet": {
    "last_updated": "2025-07-22T18:19:48.190890",
    "file_hash": "d2a26aebc1649688b06930c5fbc745a5"
  },
  "narcod_ping": {
    "last_updated": "2025-08-07T18:23:48.248052",
    "file_hash": "0105ede4c8a9821abb1c46cd0f70e11a"
  },
  "narenjvpn": {
    "last_updated": "2025-08-06T18:22:58.666536",
    "file_hash": "80c47e01d7dd9440b7efafc01aea31dd"
  },
  "netmellianti": {
    "last_updated": "2025-08-07T06:24:45.975540",
    "file_hash": "f46b6aaaab793cb36d9f06b376b4dc47"
  },
  "noforcedheaven": {
    "last_updated": "2025-08-07T01:10:13.356198",
    "file_hash": "d5af86956b9567c23d69a5ebd551c0ea"
  },
  "ohvpn": {
    "last_updated": "2025-08-07T18:23:48.248052",
    "file_hash": "fec1bf05a2151d97e95cee7360252864"
  },
  "orange_vpns": {
    "last_updated": "2025-08-07T06:24:45.975540",
    "file_hash": "2804565d47b837393538121370aa5075"
  },
  "outline_vpn": {
    "last_updated": "2025-08-07T06:24:45.975540",
    "file_hash": "63a17af54a875b538826b4fbdc70f3ce"
  },
  "prime_verse": {
    "last_updated": "2025-08-07T12:31:42.787834",
    "file_hash": "73f73c8e6bff5100d96fc39e19461a0f"
  },
  "prong1": {
    "last_updated": "2025-08-07T01:10:13.356198",
    "file_hash": "464d9343d2cdf09b90635fabeda366ed"
  },
  "prooxyk": {
    "last_updated": "2025-08-04T06:50:54.999386",
    "file_hash": "89a1ccef3af5c12b49d92c9dc8495ef3"
  },
  "proxy_v2ray_meli": {
    "last_updated": "2025-08-07T01:10:13.356198",
    "file_hash": "632edef407bd50f022aa1306eddf1a36"
  },
  "proxyfn": {
    "last_updated": "2025-08-06T18:22:58.666536",
    "file_hash": "546ddd6e459c463453a5522fc058a92a"
  },
  "proxygodratmand": {
    "last_updated": "2025-08-07T12:31:42.787834",
    "file_hash": "e38fe1bd2a1771f530a66ce2eb44e930"
  },
  "proxystore11": {
    "last_updated": "2025-08-07T01:10:13.356198",
    "file_hash": "aa9fa3cd516ba3b92a8950dbceaeb198"
  },
  "pruoxyi": {
    "last_updated": "2025-08-14T20:27:17.949126",
    "file_hash": "da57a2400f66f881ac77f2c99a8a707c"
  },
  "puni_shop_v2rayng": {
    "last_updated": "2025-07-22T18:19:48.190890",
    "file_hash": "e7c737fd4286a56b8eea497cbacb505c"
  },
  "rnrifci": {
    "last_updated": "2025-07-22T18:19:48.190890",
    "file_hash": "dcecf8217707c7331ecba7f81e2a4356"
  },
  "safenet_server": {
    "last_updated": "2025-08-07T12:31:42.787834",
    "file_hash": "67585f5ea3ae9b3ba05a7e16a1b16261"
  },
  "saghivpnx": {
    "last_updated": "2025-08-07T06:24:45.975540",
    "file_hash": "520586688a18c0dd282bcc2492673e7a"
  },
  "savagev2ray": {
    "last_updated": "2025-08-07T06:24:45.975540",
    "file_hash": "3b37628edbd8d2baa71bda31086dbd04"
  },
  "siigmavpn": {
    "last_updated": "2025-08-14T20:27:17.949126",
    "file_hash": "ad9accfd00dc5996739afcdf2addf7b3"
  },
  "sobi_vpn": {
    "last_updated": "2025-08-06T18:22:58.666536",
    "file_hash": "935b6255aee4782115d0e503f61fcffb"
  },
  "sobyv2ray": {
    "last_updated": "2025-08-14T20:27:17.949126",
    "file_hash": "633c56085a959669c59aad58aeb47c91"
  },
  "sockss_http": {
    "last_updated": "2025-08-07T18:23:48.248052",
    "file_hash": "2d57a691b6a98b002b47de90acf3458d"
  },
  "specxtech": {
    "last_updated": "2025-07-22T18:19:48.190890",
    "file_hash": "55c068c732ff3762c3d97f9099096112"
  },
  "spikevpn": {
    "last_updated": "2025-08-07T12:31:42.787834",
    "file_hash": "fecbe6eca60b137d0e561e17f3429c04"
  },
  "srcvpn": {
    "last_updated": "2025-07-22T18:19:48.190890",
    "file_hash": "1a0535003591bf996d4fd875c4d0ae07"
  },
  "ssrsub": {
    "last_updated": "2025-08-07T18:23:48.248052",
    "file_hash": "a74c78ceed2a7b29a18c2abfeb741664"
  },
  "summertimeus": {
    "last_updated": "2025-08-07T01:10:13.356198",
    "file_hash": "bdba425402d9790970d6e577d12843d2"
  },
  "teslaateam": {
    "last_updated": "2025-08-07T12:31:42.787834",
    "file_hash": "be17516eb745a8c892a899e3a9065a68"
  },
  "thefreedomvpn": {
    "last_updated": "2025-08-07T12:31:42.787834",
    "file_hash": "356c0fc287fafbd57ac16c110ac04b32"
  },
  "tinynetvpn": {
    "last_updated": "2025-08-07T18:23:48.248052",
    "file_hash": "0eae5aa718b092f8d0d9d278562f4255"
  },
  "tokavpn": {
    "last_updated": "2025-07-22T18:19:48.190890",
    "file_hash": "53fc671dd67d030b13f4c9b6070809b8"
  },
  "tondroconfig": {
    "last_updated": "2025-08-05T01:10:55.077916",
    "file_hash": "7a5be42a3804584ff31a27d5b74cd7cc"
  },
  "toxicvid": {
    "last_updated": "2025-08-14T20:27:17.949126",
    "file_hash": "5874ccf1bd8928b9b6f290854737e9da"
  },
  "tv_v2ray": {
    "last_updated": "2025-08-07T01:10:13.356198",
    "file_hash": "67c0b9a99e791e12202d5d8f174f47d9"
  },
  "uciranir": {
    "last_updated": "2025-08-06T18:22:58.666536",
    "file_hash": "f43a5410c4c211b966a6e468a4a9f97a"
  },
  "unblocker_vpn": {
    "last_updated": "2025-07-22T18:19:48.190890",
    "file_hash": "c7851d191e5bd8a382b8cc9f4ddb17f8"
  },
  "v2aray_v2": {
    "last_updated": "2025-08-04T06:50:54.999386",
    "file_hash": "caaaa4f0292f37b707f1008fc0322bea"
  },
  "v2aryng_vpn": {
    "last_updated": "2025-08-14T20:27:17.949126",
    "file_hash": "7b3d1ea81bd00e911bb6e57a1eda7519"
  },
  "v2gama": {
    "last_updated": "2025-08-07T01:10:13.356198",
    "file_hash": "56b076cfbd2b346b5d4d6bc8b019e56f"
  },
  "v2graphy": {
    "last_updated": "2025-08-07T12:31:42.787834",
    "file_hash": "4c6b5bbffd04552497712c9aa9540015"
  },
  "v2net_iran": {
    "last_updated": "2025-08-07T12:31:42.787834",
    "file_hash": "88d58efe197c847417b8de42604c22fb"
  },
  "v2ngfast": {
    "last_updated": "2025-08-09T02:18:08.966063",
    "file_hash": "e54e66ff8e2c5868c693e4b4bdf4a9ef"
  },
  "v2proxfree": {
    "last_updated": "2025-08-07T01:10:13.356198",
    "file_hash": "95848fca79829d68582425c5ad7355ad"
  },
  "v2raand": {
    "last_updated": "2025-08-04T06:50:54.999386",
    "file_hash": "4985860370b58705a68100dd4b3da2dd"
  },
  "v2ray_6": {
    "last_updated": "2025-08-07T18:23:48.248052",
    "file_hash": "21bc3bcbf60bbf3a866c6f306b3190ef"
  },
  "v2ray_fark": {
    "last_updated": "2025-08-07T12:31:42.787834",
    "file_hash": "0005962c07fef959861523c87f8ebcd9"
  },
  "v2ray_fd": {
    "last_updated": "2025-07-22T18:19:48.190890",
    "file_hash": "a5d50a5dee23e08e83357b7c0800e5bd"
  },
  "v2ray_ng": {
    "last_updated": "2025-08-07T18:23:48.248052",
    "file_hash": "486b693838d19e98a4d67f7c9932472f"
  },
  "v2ray_one1": {
    "last_updated": "2025-08-07T12:31:42.787834",
    "file_hash": "e7df7a673d8c92469b7350216c00ddbc"
  },
  "v2ray_swhil": {
    "last_updated": "2025-08-07T01:10:13.356198",
    "file_hash": "a73f5e8c24e3c1523346afa88110c42e"
  },
  "v2raybluecrystal": {
    "last_updated": "2025-08-07T12:31:42.787834",
    "file_hash": "dc71bc3cc70735c26861e2b323a50dc4"
  },
  "v2rayfree_irr": {
    "last_updated": "2025-08-07T18:23:48.248052",
    "file_hash": "c371762bb799e95b5b98663acc18ff55"
  },
  "v2rayi5": {
    "last_updated": "2025-08-06T06:25:33.942702",
    "file_hash": "771fc00a08c8e81fea1e1775584d6717"
  },
  "v2rayn5": {
    "last_updated": "2025-08-07T06:24:45.975540",
    "file_hash": "c3bf77d011be6af0add4b0e8816d0262"
  },
  "v2rayng954": {
    "last_updated": "2025-08-14T20:27:17.949126",
    "file_hash": "7b3c88aa8569b783eb77e6a258f8fac0"
  },
  "v2rayng_1378": {
    "last_updated": "2025-08-07T01:10:13.356198",
    "file_hash": "d617a82f00aef8063e895bf4221306ee"
  },
  "v2rayngcloud": {
    "last_updated": "2025-08-07T01:10:13.356198",
    "file_hash": "6e40fedea9bb9b06e5eb426cfe639b16"
  },
  "v2rayngcustom": {
    "last_updated": "2025-08-07T18:23:48.248052",
    "file_hash": "65e3551e833197df66a8c2a462ae4759"
  },
  "v2rayngfreee": {
    "last_updated": "2025-07-22T18:19:48.190890",
    "file_hash": "d93346b1f6e15a24c73a9ce46a386b84"
  },
  "v2rayngv": {
    "last_updated": "2025-08-07T06:24:45.975540",
    "file_hash": "2b5256c6ae168377e7366378ba39e681"
  },
  "v2rayngvpn": {
    "last_updated": "2025-08-07T06:24:45.975540",
    "file_hash": "5d7262820d5284c8352c767332982119"
  },
  "v2rayngvpnn": {
    "last_updated": "2025-07-22T18:19:48.190890",
    "file_hash": "3640be39dfd9f3b56ef3e007bb6729b4"
  },
  "v_2rayngvpn": {
    "last_updated": "2025-08-07T01:10:13.356198",
    "file_hash": "cc82bdea450b9e4ed9962f53b6d05e22"
  },
  "varn_net": {
    "last_updated": "2025-08-06T06:25:33.942702",
    "file_hash": "45a30995fee37f7246915621e46e0f3b"
  },
  "vipfastspeed": {
    "last_updated": "2025-08-06T01:09:59.624461",
    "file_hash": "29016473b61c9f838414a3cf1fb8f7ba"
  },
  "virav2ray": {
    "last_updated": "2025-08-14T20:27:17.949126",
    "file_hash": "cea658a73c49bdb47a599f85de934374"
  },
  "vless_config": {
    "last_updated": "2025-08-07T01:10:13.356198",
    "file_hash": "d1b812feb196f127236ac6b73457386f"
  },
  "vmess_iran": {
    "last_updated": "2025-08-14T20:27:17.949126",
    "file_hash": "36d9bbbdc5cd04f8441bec6f038621de"
  },
  "vmess_vless_v2rayng": {
    "last_updated": "2025-08-07T01:10:13.356198",
    "file_hash": "a2e618511f464a5fae09429cdf85498c"
  },
  "vmessiran": {
    "last_updated": "2025-07-22T18:19:48.190890",
    "file_hash": "64ea7586ca570f61dc0b0645e9590c81"
  },
  "vmesskhodam_vip": {
    "last_updated": "2025-08-07T12:31:42.787834",
    "file_hash": "7941d179200512bfd96090fe2c0522bd"
  },
  "vp22ray": {
    "last_updated": "2025-08-06T01:09:59.624461",
    "file_hash": "ed299b98b4312fbf7b4b5e95349754b1"
  },
  "vpfreen": {
    "last_updated": "2025-08-07T12:31:42.787834",
    "file_hash": "af47a01c3b07323ba59082b7b0216ba6"
  },
  "vpn707": {
    "last_updated": "2025-08-07T06:24:45.975540",
    "file_hash": "49a01bcb0a0b541f65eb94f63713f9ed"
  },
  "vpn_kanfik": {
    "last_updated": "2025-08-14T20:27:17.949126",
    "file_hash": "1bd6e8cad96419bb63e6a87d490ac992"
  },
  "vpn_mikey": {
    "last_updated": "2025-07-23T01:06:19.614068",
    "file_hash": "55c106f6b8f2f5938f008ef39963a2d1"
  },
  "vpnbigbang": {
    "last_updated": "2025-07-23T01:06:19.614068",
    "file_hash": "ff45c855d475488b8f923e8cb56a282e"
  },
  "Free_Internet_Iran": {
    "last_updated": "2025-08-14T20:27:17.949126",
    "file_hash": "9523b9cd6553da186ce5d630da1a3183"
  },
  "ARv2ray": {
    "last_updated": "2025-08-07T18:23:48.248052",
    "file_hash": "25c2da1b616910fe2a477bfd1bec97b3"
  },
  "UnlimitedDev": {
    "last_updated": "2025-08-07T18:23:48.248052",
    "file_hash": "9766c77229b7cdf3aaa4448b69d36c16"
  },
  "Vpn_Mikey": {
    "last_updated": "2025-08-04T06:26:37.462148",
    "file_hash": "74d8d9d58f25a18015907914548c428e"
  },
  "SVNTEAM": {
    "last_updated": "2025-08-14T20:27:17.949126",
    "file_hash": "83b24956c2f8600fafae825c8a15c650"
  },
  "V2RAY_VMESS_free": {
    "last_updated": "2025-08-14T20:27:17.949126",
    "file_hash": "cf6afcc7af04b3fcdfd0bd1c7a8f04cd"
  },
  "ShadowsocksM": {
    "last_updated": "2025-07-28T01:10:30.809232",
    "file_hash": "a494ae1ce896cd8b8dbb42a84e0fb2f9"
  },
  "Awlix_ir": {
    "last_updated": "2025-08-07T18:23:48.248052",
    "file_hash": "85b4a05abe11f6beb2dae36824069bc5"
  },
  "MTProto_666": {
    "last_updated": "2025-08-14T20:27:17.949126",
    "file_hash": "979da6bd371ae1bf8e620a74a89b3325"
  },
  "v2rayPort": {
    "last_updated": "2025-08-14T20:27:17.949126",
    "file_hash": "8d70f002a12b9198def54bb72612199b"
  },
  "v2rayyNGvpn": {
    "last_updated": "2025-07-23T01:58:33.088087",
    "file_hash": "5e1d267b485a85ca8a7538517dba0c0f"
  },
  "Digiv2ray": {
    "last_updated": "2025-08-07T18:23:48.248052",
    "file_hash": "bf5a653bd241fb9f9d96eb8b6afc34fe"
  },
  "DigiV2ray23": {
    "last_updated": "2025-08-14T20:27:17.949126",
    "file_hash": "55eb95bcf474daa711703920a31e21f2"
  },
  "RxV2ray": {
    "last_updated": "2025-08-07T18:23:48.248052",
    "file_hash": "edaa98f33a1168118acc107822ffe422"
  },
  "V2rayngninja": {
    "last_updated": "2025-08-07T18:23:48.248052",
    "file_hash": "942a488f797752d6e105d326491c2186"
  },
  "Lockey_VPN": {
    "last_updated": "2025-08-04T06:26:37.462148",
    "file_hash": "d21ff41710eeef455974018784cf288a"
  },
  "V2ray1_Ng": {
    "last_updated": "2025-08-07T18:23:48.248052",
    "file_hash": "7d6c2bc76215ea76da24e901715884e0"
  },
  "fastvpnorummobile": {
    "last_updated": "2025-08-14T20:27:17.949126",
    "file_hash": "24cf5e3a18e7d15ffb98e5633eb06120"
  },
  "v2_fast": {
    "last_updated": "2025-08-14T20:27:17.949126",
    "file_hash": "ce0c7236c5582e3a150b06d9a0f9440e"
  },
  "VPNCUSTOMIZE": {
    "last_updated": "2025-08-07T18:23:48.248052",
    "file_hash": "f585f480472bc9b02798cbcdab975b1a"
  },
  "V_2rayngVpn": {
    "last_updated": "2025-08-07T01:10:13.356198",
    "file_hash": "cc82bdea450b9e4ed9962f53b6d05e22"
  },
  "vmessorg": {
    "last_updated": "2025-08-07T06:24:45.975540",
    "file_hash": "3175d65c89a098ca1165db277c511943"
  },
  "lrnbymaa": {
    "last_updated": "2025-08-04T06:50:54.999386",
    "file_hash": "25c5cae87950636205b4e74bc50d13ab"
  },
  "nofiltering2": {
    "last_updated": "2025-08-14T20:27:17.949126",
    "file_hash": "6851b803c379602158745468bfa59108"
  },
  "v2rayNG_Matsuri": {
    "last_updated": "2025-08-07T01:10:13.356198",
    "file_hash": "ec25e48cd92a308a427cabf3977ca789"
  },
  "lightning6": {
    "last_updated": "2025-08-13T20:26:31.901431",
    "file_hash": "522f1b0d4399eb0c9afa78c17daeb8af"
  },
  "v2logy": {
    "last_updated": "2025-08-14T20:27:17.949126",
    "file_hash": "d3bdc89b1e2276f6d1e77a7484bea883"
  },
  "FalconPolV2rayNG": {
    "last_updated": "2025-08-14T14:20:13.719500",
    "file_hash": "1d47ce2c02a886970f8d15685dae36ba"
  },
  "Parsashonam": {
    "last_updated": "2025-08-07T01:10:13.356198",
    "file_hash": "8fd8416359c968fb95c3b009465110c3"
  },
  "proxy_kafee": {
    "last_updated": "2025-08-07T18:23:48.248052",
    "file_hash": "312a055e9bc3311858174dd087537f39"
  },
  "XsV2ray": {
    "last_updated": "2025-08-07T01:10:13.356198",
    "file_hash": "bd6af2fc085372bcf8e80629c04a695a"
  },
  "v2_team": {
    "last_updated": "2025-08-07T12:31:42.787834",
    "file_hash": "d7b786b9b3f87a5aa06662bac7649c48"
  },
  "DeamNet_Proxy": {
    "last_updated": "2025-08-07T12:31:42.787834",
    "file_hash": "b542fbb06070d20af8a30907dbb5c0e5"
  },
  "vpn_go67": {
    "last_updated": "2025-08-07T12:31:42.787834",
    "file_hash": "937699ce07f8b74e27305e065d5ef87b"
  },
  "GozargahVPN": {
    "last_updated": "2025-08-07T06:24:45.975540",
    "file_hash": "f1a5e8b1a7eb22bf9487a19b7875f95f"
  },
  "NIM_VPN_ir": {
    "last_updated": "2025-08-14T20:27:17.949126",
    "file_hash": "4d663f5606a95d6430aa557ae78b25d7"
  },
  "CUSTOMVPNSERVER": {
    "last_updated": "2025-08-07T18:23:48.248052",
    "file_hash": "a51175d1990d4ba14ea2efbd747b5ad4"
  },
  "Capoit": {
    "last_updated": "2025-08-07T18:23:48.248052",
    "file_hash": "e6992bf47d67278e373438eaed707a43"
  },
  "SSRSUB": {
    "last_updated": "2025-08-07T18:23:48.248052",
    "file_hash": "a74c78ceed2a7b29a18c2abfeb741664"
  },
  "adamak_vpn": {
    "last_updated": "2025-08-07T06:24:45.975540",
    "file_hash": "8dd8660b600552f402ccb48db55fb4e4"
  },
  "alienvpn402": {
    "last_updated": "2025-08-04T06:50:54.999386",
    "file_hash": "7bab873bdd70a9f3dc14b56c7b2b4260"
  },
  "antifilterjadid": {
    "last_updated": "2025-08-07T06:24:45.975540",
    "file_hash": "d17b41f1531fa54d2d6bfaf1ca2e2fee"
  },
  "clubvpn443": {
    "last_updated": "2025-08-14T20:27:17.949126",
    "file_hash": "e17581bb584bbd0df43542c7ab8e7e42"
  },
  "configscenter": {
    "last_updated": "2025-08-07T01:10:13.356198",
    "file_hash": "b33f73667acc7f9ae646b042b9de3cd6"
  },
  "dailyv2ray": {
    "last_updated": "2025-08-06T18:22:58.666536",
    "file_hash": "b3f3fa9accc4fdb5e1a9aeddf9f6ac2b"
  },
  "deli_servers": {
    "last_updated": "2025-08-07T01:10:13.356198",
    "file_hash": "951a06f39dfded4b294e1df8e4f2ac51"
  },
  "donald_config": {
    "last_updated": "2025-08-07T12:31:42.787834",
    "file_hash": "dd79f94353b6bd70215d78b4525c4a9e"
  },
  "falconpolv2rayng": {
    "last_updated": "2025-08-05T18:24:27.926148",
    "file_hash": "752b93f6337b86a5d6415d8239852418"
  },
  "free_vpn02": {
    "last_updated": "2025-08-07T06:24:45.975540",
    "file_hash": "374c57724c125e17064a285fb5151c73"
  },
  "freev2flyng": {
    "last_updated": "2025-08-07T18:23:48.248052",
    "file_hash": "1f3b41115b95257b547c305ffa8c1ab4"
  },
  "fsv2ray": {
    "last_updated": "2025-08-07T12:31:42.787834",
    "file_hash": "2e861e3368e2a81cb48788ad3c2bfc5e"
  },
  "moftinet": {
    "last_updated": "2025-08-04T06:50:54.999386",
    "file_hash": "21d5917f44ae412e20060ed2855c9175"
  },
  "outline_ir": {
    "last_updated": "2025-08-14T20:27:17.949126",
    "file_hash": "4db20452b17b4413fe8af9de5f15b716"
  },
  "oxir_vpn": {
    "last_updated": "2025-08-07T01:10:13.356198",
    "file_hash": "697810b030c13c3be1221665c42c9236"
  },
  "pardazeshvpn": {
    "last_updated": "2025-08-06T18:22:58.666536",
    "file_hash": "6a61b7751efd1527bcd341298c75b2e9"
  },
  "satoshivpn": {
    "last_updated": "2025-08-07T01:10:13.356198",
    "file_hash": "8a2c95810bdefee059682f1c70b7479e"
  },
  "tehranargo": {
    "last_updated": "2025-08-14T20:27:17.949126",
    "file_hash": "eb90b3e0192b9a2d11dacf28647aec15"
  },
  "tiny_vpn_official": {
    "last_updated": "2025-08-07T01:10:13.356198",
    "file_hash": "b3e5a3a5856fca4daf37025c17c85364"
  },
  "topvpn02": {
    "last_updated": "2025-08-07T06:24:45.975540",
    "file_hash": "6724954ac7dbe1afe403ad80ed3cfac1"
  },
  "v2ray1_ng": {
    "last_updated": "2025-08-07T01:10:13.356198",
    "file_hash": "a31b3419d1115727fd2e0ac50104a6a7"
  },
  "v2ray_83": {
    "last_updated": "2025-08-07T06:24:45.975540",
    "file_hash": "98bdcc7dca6f123909da7ca31d1781d1"
  },
  "v2raycollectordonate": {
    "last_updated": "2025-08-07T18:23:48.248052",
    "file_hash": "0dfe6badc94796a10b87355a54067359"
  },
  "v2rayfa": {
    "last_updated": "2025-08-04T06:50:54.999386",
    "file_hash": "957dba4198acfd87d8e6c22a1d9c7107"
  },
  "v2raying": {
    "last_updated": "2025-08-07T06:24:45.975540",
    "file_hash": "2a7348a4bc4253d2a0a7e0fcdc486a97"
  },
  "v2rayng_81": {
    "last_updated": "2025-08-14T20:27:17.949126",
    "file_hash": "c27b2f97a8f1ae17a27f61c50b03df16"
  },
  "v2rayngrit": {
    "last_updated": "2025-08-07T12:31:42.787834",
    "file_hash": "b9e6abe6ad7da8b5f63208f9d006d1e1"
  },
  "v2rayngte": {
    "last_updated": "2025-08-07T01:10:13.356198",
    "file_hash": "108cd39f70ab6efcc6841d55abea706b"
  },
  "v2rayza": {
    "last_updated": "2025-08-07T01:10:13.356198",
    "file_hash": "7d707a09751aa4e700f904444f186889"
  },
  "v2rray_ng": {
    "last_updated": "2025-08-07T06:24:45.975540",
    "file_hash": "839fce43cdb24bf604ace8d2c241bd88"
  },
  "vboxpanel": {
    "last_updated": "2025-08-04T06:50:54.999386",
    "file_hash": "eb53fe75dca359caf9b8597ef7300117"
  },
  "vpn_v2rayng_gap": {
    "last_updated": "2025-08-07T01:10:13.356198",
    "file_hash": "ff58032569e38fc14ef385f7362de42b"
  },
  "vpncustomize": {
    "last_updated": "2025-08-07T06:24:45.975540",
    "file_hash": "9cd742e93fe32f7c4e6bb74c02e3f678"
  },
  "vpnkanfik": {
    "last_updated": "2025-08-04T06:50:54.999386",
    "file_hash": "e34137890240f33983384e04f5403a0f"
  },
  "vpnmk1": {
    "last_updated": "2025-08-07T01:10:13.356198",
    "file_hash": "d66bc382e8662e9a64f4687425648686"
  },
  "vpnv2rayonline": {
    "last_updated": "2025-08-04T06:50:54.999386",
    "file_hash": "f455b282dab533870d16c61638c82883"
  },
  "vpnv2raytop": {
    "last_updated": "2025-08-07T06:24:45.975540",
    "file_hash": "28c3397402a5c71e3a78d290c76c4f30"
  },
  "webhube": {
    "last_updated": "2025-08-07T01:10:13.356198",
    "file_hash": "1f810c971bd233bbb0837ff0a6493349"
  },
  "yekoyekvpn": {
    "last_updated": "2025-08-07T06:24:45.975540",
    "file_hash": "6bddd4c5e5b2f285428dfd151260467d"
  },
  "yxjnode": {
    "last_updated": "2025-08-07T01:10:13.356198",
    "file_hash": "0faad102a7aa539151575994ee357651"
  },
  "apple_x1": {
    "last_updated": "2025-08-07T06:24:45.975540",
    "file_hash": "986891366891bcf8dde2458df90fe4ab"
  },
  "artemisvpn1": {
    "last_updated": "2025-08-13T09:02:26.298662",
    "file_hash": "88a5ed85a350e7f3c420f138519ad128"
  },
  "black8rose": {
    "last_updated": "2025-08-14T20:27:17.949126",
    "file_hash": "be95e3750f43aad88b45f321f0a1abd1"
  },
  "bolbolvpn": {
    "last_updated": "2025-08-14T20:27:17.949126",
    "file_hash": "82eb9f2ac9ff4952d26d3fec0dd1af5e"
  },
  "capoit": {
    "last_updated": "2025-08-07T18:23:48.248052",
    "file_hash": "e6992bf47d67278e373438eaed707a43"
  },
  "club_vpn9": {
    "last_updated": "2025-08-14T20:27:17.949126",
    "file_hash": "a9e683e368f082f90582bf47791e34ca"
  },
  "confingv2raayng": {
    "last_updated": "2025-08-06T18:22:58.666536",
    "file_hash": "75d21c8915670293698647b20b742523"
  },
  "darkma3ter24": {
    "last_updated": "2025-08-04T06:50:54.999386",
    "file_hash": "9bc574ce114f5865f3ff6c4c462013b6"
  },
  "game_file2020": {
    "last_updated": "2025-08-07T18:23:48.248052",
    "file_hash": "a3550a6898afbc99c680c850053e5c24"
  },
  "iranbfilter": {
    "last_updated": "2025-08-06T18:22:58.666536",
    "file_hash": "4ccc7c3e9bbbd59fd8093cdf92e55301"
  },
  "iraniv2ray": {
    "last_updated": "2025-08-04T06:50:54.999386",
    "file_hash": "c179323b05fef773b4ff959cd8f059c8"
  },
  "iranvipnet": {
    "last_updated": "2025-08-04T06:50:54.999386",
    "file_hash": "ff637107bd6f65d9b6438a37b4ab5afe"
  },
  "jiedianf": {
    "last_updated": "2025-08-14T20:27:17.949126",
    "file_hash": "63183b57d6a08fc6a2866637f829b1d6"
  },
  "jiujied": {
    "last_updated": "2025-08-07T06:24:45.975540",
    "file_hash": "a55e768c5370e880bc23a6cea13b5809"
  },
  "kuto_proxy2": {
    "last_updated": "2025-08-06T18:22:58.666536",
    "file_hash": "58c5fbd4c0d639c903096acbd4cc9d6f"
  },
  "lax_vpn": {
    "last_updated": "2025-08-07T01:10:13.356198",
    "file_hash": "c7d58e35d78ba165b2bd8929a4122677"
  },
  "m_buy": {
    "last_updated": "2025-08-07T01:10:13.356198",
    "file_hash": "5459bfc8b1d13e070fa0a15b0246d853"
  },
  "mrvpn1403": {
    "last_updated": "2025-08-14T20:27:17.949126",
    "file_hash": "9f5b9ae29faaab94cf1469d524e576a8"
  },
  "msv2ray": {
    "last_updated": "2025-08-07T06:24:45.975540",
    "file_hash": "5b0af4fb2bc849b7fb85c0a2cb3385f0"
  },
  "mtproxy22_v2ray": {
    "last_updated": "2025-08-06T06:25:33.942702",
    "file_hash": "a6834da1cdf21885086804a904ddb506"
  },
  "mxv2ray": {
    "last_updated": "2025-08-07T01:10:13.356198",
    "file_hash": "26e2d18c21d33b56eb89f42a04698524"
  },
  "nepo_v2ray": {
    "last_updated": "2025-08-07T12:31:42.787834",
    "file_hash": "88b251a96fcffb745dca03068cb8349e"
  },
  "netspeedservice": {
    "last_updated": "2025-08-07T01:10:13.356198",
    "file_hash": "e9c3531a2868c775ad0d9bc0ffa6467c"
  },
  "nicolv2ray": {
    "last_updated": "2025-08-04T06:50:54.999386",
    "file_hash": "312bcc5c30146ca5b567eaa1f20ab904"
  },
  "novinology": {
    "last_updated": "2025-08-07T12:31:42.787834",
    "file_hash": "d775c618902e8861c081fafd1a183baf"
  },
  "private_access_guard_vpn": {
    "last_updated": "2025-08-06T12:31:31.275312",
    "file_hash": "557420ca07908170e07eb08ef6f98a3a"
  },
  "proxie": {
    "last_updated": "2025-08-04T06:50:54.999386",
    "file_hash": "65d69349860cd71f482d9be9517c98bf"
  },
  "renetvpn": {
    "last_updated": "2025-08-14T20:27:17.949126",
    "file_hash": "cfff7a23910f6b41f4c384ff37ec9b59"
  },
  "rk_filtershking": {
    "last_updated": "2025-08-06T18:22:58.666536",
    "file_hash": "1490eb10e987bafc4fdfe3c05432b56d"
  },
  "saferoadnet": {
    "last_updated": "2025-08-07T06:24:45.975540",
    "file_hash": "13797a40b166ffb9e8f4263dd19fef8f"
  },
  "shadowproxy66": {
    "last_updated": "2025-08-06T18:22:58.666536",
    "file_hash": "2302d7aa32850998f4962874b4b22c38"
  },
  "shconfig": {
    "last_updated": "2025-08-07T06:24:45.975540",
    "file_hash": "1d03eca36478448ddfb2c50a651b87c7"
  },
  "skivpn": {
    "last_updated": "2025-08-14T20:27:17.949126",
    "file_hash": "def17233fea4c9d707825444d685e6c8"
  },
  "tc_v2ray": {
    "last_updated": "2025-08-07T06:24:45.975540",
    "file_hash": "d0fcf636c2f80e939654a2d60adf4ff5"
  },
  "telmavpn": {
    "last_updated": "2025-08-06T06:25:33.942702",
    "file_hash": "c3409df3ac24628933a92da15c5a59ad"
  },
  "tunssh": {
    "last_updated": "2025-08-04T06:50:54.999386",
    "file_hash": "944d42a52390e02b23dac935b82a4680"
  },
  "turboo_server": {
    "last_updated": "2025-08-14T20:27:17.949126",
    "file_hash": "8ebc04cd2050341a5157ef57475c00a3"
  },
  "univstar": {
    "last_updated": "2025-08-06T18:22:58.666536",
    "file_hash": "6cf95cbbf0b79823b99d9474a72c0af1"
  },
  "v2hamid": {
    "last_updated": "2025-08-07T12:31:42.787834",
    "file_hash": "a4bbe8f20ae45df9bc5f20f6422c8e31"
  },
  "v2icy": {
    "last_updated": "2025-08-07T01:10:13.356198",
    "file_hash": "94197f39e09f386fc9ee3caa0f59e466"
  },
  "v2ray_inter": {
    "last_updated": "2025-08-06T18:22:58.666536",
    "file_hash": "ecf6c33378f703b1b1126c4a334bb52d"
  },
  "v2ray_onli": {
    "last_updated": "2025-08-07T12:31:42.787834",
    "file_hash": "388f6538aaede4bc27a9a8002a6dbe89"
  },
  "v2ray_reality_new": {
    "last_updated": "2025-08-07T06:24:45.975540",
    "file_hash": "ceac5569e457dacce9cb87ad7170ea8a"
  },
  "v2ray_youtube": {
    "last_updated": "2025-08-07T12:31:42.787834",
    "file_hash": "0716881d74c37d7bfb5f76af3e606de0"
  },
  "v2rayargon": {
    "last_updated": "2025-08-07T01:10:13.356198",
    "file_hash": "be94e5ca715eac5403caff6e5f1dd7fc"
  },
  "v2rayfast_7": {
    "last_updated": "2025-08-07T12:31:42.787834",
    "file_hash": "89d16fd7eb60d04188a05fdb92c410bf"
  },
  "v2rayip1": {
    "last_updated": "2025-08-14T20:27:17.949126",
    "file_hash": "fea81a47c0f625c142b35f0e107cb309"
  },
  "v2rayng3": {
    "last_updated": "2025-08-07T18:23:48.248052",
    "file_hash": "6a56d722f4635a4689784f656a513946"
  },
  "v2rayng_v2_ray": {
    "last_updated": "2025-08-07T06:24:45.975540",
    "file_hash": "a0f0b4a09067cff2d2334c98e83b5039"
  },
  "v2rayngchaannel": {
    "last_updated": "2025-08-07T06:24:45.975540",
    "file_hash": "3443faaa635cf12df99391969681495e"
  },
  "v2rayngn": {
    "last_updated": "2025-08-06T18:22:58.666536",
    "file_hash": "30b5b51b4d521e2adc6c0b8fa4208be8"
  },
  "v2rayngrr13": {
    "last_updated": "2025-08-07T06:24:45.975540",
    "file_hash": "892d15cd2355afb4d7924f04ec4bbad7"
  },
  "v2rayopen": {
    "last_updated": "2025-08-07T01:10:13.356198",
    "file_hash": "42c118597bfe2835fbe03b617be13df7"
  },
  "v2rayshop_m": {
    "last_updated": "2025-08-07T12:31:42.787834",
    "file_hash": "2b3c335c6c4b8c98f4555aabbd828642"
  },
  "v2rayvpnchannel": {
    "last_updated": "2025-08-07T18:23:48.248052",
    "file_hash": "b4fa1558b8efca6559dd92d71f687212"
  },
  "v2roay": {
    "last_updated": "2025-08-07T01:10:13.356198",
    "file_hash": "3cab5bee9aeb6f6fae264216b61e9e68"
  },
  "v2rplus": {
    "last_updated": "2025-08-14T20:27:17.949126",
    "file_hash": "774064ce96f883d83638d7d4bcac068e"
  },
  "v2ryorg": {
    "last_updated": "2025-08-06T18:22:58.666536",
    "file_hash": "2d4849983395cb9650bd417bbbdaabca"
  },
  "v2safee": {
    "last_updated": "2025-08-07T06:24:45.975540",
    "file_hash": "a5908dcf553490d63238b1cd247c7f38"
  },
  "vmess_ir": {
    "last_updated": "2025-08-14T20:27:17.949126",
    "file_hash": "539cbd53e41fa0f30fdc147b07abe181"
  },
  "vpn_gaming": {
    "last_updated": "2025-08-07T01:10:13.356198",
    "file_hash": "3bdcfa58987282f973bf4968a8f87d40"
  },
  "vpn_storm": {
    "last_updated": "2025-08-06T18:22:58.666536",
    "file_hash": "8dc6a0c130367830ffb8dc3a3041aee0"
  },
  "vpnowl": {
    "last_updated": "2025-08-07T18:23:48.248052",
    "file_hash": "704f67a725ee63e117cb803d9f83cc51"
  },
  "vpnstorefast": {
    "last_updated": "2025-08-07T01:10:13.356198",
    "file_hash": "88d659f84d48b65b617f3194070085ac"
  },
  "vpnxyam_ir": {
    "last_updated": "2025-08-07T01:10:13.356198",
    "file_hash": "d49f59bb72a8d3a1f6d4fc7fb3d8724a"
  },
  "womanlifefreedomvpn": {
    "last_updated": "2025-08-07T06:24:45.975540",
    "file_hash": "85d30bc31b50a96b3beda2ae29a1f059"
  },
  "world_vmess": {
    "last_updated": "2025-08-07T18:23:48.248052",
    "file_hash": "7e6d22a655dd94dd2d892c3e0ee12b79"
  },
  "xiv2ray": {
    "last_updated": "2025-08-07T06:24:45.975540",
    "file_hash": "98bdcc7dca6f123909da7ca31d1781d1"
  },
  "xrayzxn": {
    "last_updated": "2025-08-07T01:10:13.356198",
    "file_hash": "25396a1eacb8c4f6f81b8c060ff4c760"
  },
  "zdyz2": {
    "last_updated": "2025-08-04T06:50:54.999386",
    "file_hash": "53fc7442a032721d6053e81b0c06e348"
  },
  "zede_filteri": {
    "last_updated": "2025-08-07T01:10:13.356198",
    "file_hash": "eb44ba020694319ef314403113f34151"
  },
  "kingspeedchanel": {
    "last_updated": "2025-08-07T01:10:13.356198",
    "file_hash": "2cf98314376a2528abc44806a0162fe3"
  },
  "MsV2ray": {
    "last_updated": "2025-08-14T20:27:17.949126",
    "file_hash": "3a68331eafe03c97691954cd625cda05"
  },
  "Outline_Vpn": {
    "last_updated": "2025-08-14T14:20:13.719500",
    "file_hash": "99ed461e5ec1e80290c4b5b47f5d7c71"
  },
  "ServerNett": {
    "last_updated": "2025-08-06T12:31:31.275312",
    "file_hash": "57c4a23b3399a5060d4ba1da8404c06f"
  },
  "kingofilter": {
    "last_updated": "2025-08-07T06:24:45.975540",
    "file_hash": "44add3ecf78bc5480f1f9ef09f2bf470"
  },
  "ShadowProxy66": {
    "last_updated": "2025-08-07T18:23:48.248052",
    "file_hash": "2f343467fbe452d425db510e93bb4fd4"
  },
  "DirectVPN": {
    "last_updated": "2025-08-07T01:10:13.356198",
    "file_hash": "65bbc9cda3827447f251d60b1f3b0480"
  },
  "V2rayCollectorDonate": {
    "last_updated": "2025-08-06T01:09:59.624461",
    "file_hash": "4054ff48ff252df8ac314698d68d9f41"
  },
  "mftizi": {
    "last_updated": "2025-08-14T20:27:17.949126",
    "file_hash": "7fa8bb30c110c3a1185eab0f3977a4f4"
  },
  "meli_proxyy": {
    "last_updated": "2025-08-07T01:10:13.356198",
    "file_hash": "0a92a5a538e99bb659e2ac32b7d0d3cd"
  },
  "yaney_01": {
    "last_updated": "2025-08-05T18:24:27.926148",
    "file_hash": "a5007a2c4db160ccc32bfd302cc8d48c"
  },
  "wxdy666": {
    "last_updated": "2025-08-06T01:09:59.624461",
    "file_hash": "a8b55d0f07562f6e1e9883b89052b93c"
  },
  "prrofile_purple": {
    "last_updated": "2025-08-07T01:10:13.356198",
    "file_hash": "dc5ca14ab793190fccb4c15d6af6192c"
  },
  "FreakConfig": {
    "last_updated": "2025-08-07T18:23:48.248052",
    "file_hash": "afcd5cca6864abb499f907b8512d45a6"
  },
  "daredevill_404": {
    "last_updated": "2025-08-07T18:23:48.248052",
    "file_hash": "13737567b5e1c18d0aac9ebfdaa03f33"
  },
  "EliV2ray": {
    "last_updated": "2025-08-06T12:31:31.275312",
    "file_hash": "7c966ddc4d3c7a8f78a18694831a3916"
  },
  "V2rayNGn": {
    "last_updated": "2025-08-07T18:23:48.248052",
    "file_hash": "788917c1db3fa2fe4bf5580724f4797a"
  },
  "AzadNet": {
    "last_updated": "2025-08-07T01:10:13.356198",
    "file_hash": "f458ad347093d2f246097413ead7b163"
  },
  "Easy_Free_VPN": {
    "last_updated": "2025-08-14T20:27:17.949126",
    "file_hash": "fedd13e702333878bd1201906e239705"
  },
  "FOXNT": {
    "last_updated": "2025-08-07T06:24:45.975540",
    "file_hash": "8b4c470dd948cfc471768a89a8fd363e"
  },
  "FreeVlessVpn": {
    "last_updated": "2025-08-07T18:23:48.248052",
    "file_hash": "9dbf9dc0c6e44204f9037a460594817a"
  },
  "IRANVPNNET": {
    "last_updated": "2025-08-07T12:31:42.787834",
    "file_hash": "bb38d4376285a1430c9ad86744af8dbf"
  },
  "ProxyFn": {
    "last_updated": "2025-08-07T01:10:13.356198",
    "file_hash": "2d61ca261dd7ff539b97244d2b7d85e8"
  },
  "bemolatext": {
    "last_updated": "2025-08-06T18:22:58.666536",
    "file_hash": "9550bb2247f3e2196affa73651de92c3"
  },
  "digigard_vpn": {
    "last_updated": "2025-08-14T20:27:17.949126",
    "file_hash": "56711c0a568d600b6737dc31a1cbecd2"
  },
  "elitevpnv2": {
    "last_updated": "2025-08-06T06:25:33.942702",
    "file_hash": "097f43e1366dbcd86bb926594558a22a"
  },
  "flystoreir": {
    "last_updated": "2025-08-06T18:22:58.666536",
    "file_hash": "6d8eeaef3a0a204a1e18a237d65c5386"
  },
  "frev2rayng": {
    "last_updated": "2025-08-07T06:24:45.975540",
    "file_hash": "95226e1aa2b9c6a46bbce2a461fb15b2"
  },
  "ghalagyann": {
    "last_updated": "2025-08-14T20:27:17.949126",
    "file_hash": "b22803ecf983b49e71ad3bf5d80be977"
  },
  "hooshang_vpn1": {
    "last_updated": "2025-08-07T06:24:45.975540",
    "file_hash": "7c4f80c68524543aefae4ed6c9d28b5e"
  },
  "hpv2ray_official": {
    "last_updated": "2025-08-14T20:27:17.949126",
    "file_hash": "77328548af431c1462fcbaab6bbdf8d1"
  },
  "mahxray": {
    "last_updated": "2025-08-07T01:10:13.356198",
    "file_hash": "46453fcea0ef148280766af3a15e3a8f"
  },
  "mater_1345": {
    "last_updated": "2025-08-07T18:23:48.248052",
    "file_hash": "0a01a2043d9f0f382129cd66c09dfa86"
  },
  "mrv2raay": {
    "last_updated": "2025-08-07T01:10:13.356198",
    "file_hash": "44c042a630ebb37fdc7ceb93f0e54828"
  },
  "nt_safe": {
    "last_updated": "2025-08-07T01:10:13.356198",
    "file_hash": "320e3a7a37227ed606c527fcf0611da8"
  },
  "outlinev2rayng": {
    "last_updated": "2025-08-05T12:31:44.499348",
    "file_hash": "fc556634096eb0c5b1518b896f5ce726"
  },
  "pin_proxy": {
    "last_updated": "2025-08-05T18:24:27.926148",
    "file_hash": "1d2800a36bb9317f757005f2022c51ad"
  },
  "proxy_n1": {
    "last_updated": "2025-08-14T20:27:17.949126",
    "file_hash": "bb6d80064d94ecec7aa2dbef19c71ef8"
  },
  "satellitenewspersian": {
    "last_updated": "2025-08-07T18:23:48.248052",
    "file_hash": "47de1bd6ee8be0939bdceb39d5b6f520"
  },
  "shadowsockskeys": {
    "last_updated": "2025-08-06T18:22:58.666536",
    "file_hash": "9f887a5bdf5002e57106e72311cebb4a"
  },
  "teamvpnpro": {
    "last_updated": "2025-08-07T06:24:45.975540",
    "file_hash": "1f04c286077fd0acc3b5a6138e64aa99"
  },
  "toyota_proxy": {
    "last_updated": "2025-08-07T06:24:45.975540",
    "file_hash": "f8512fb4ac948610040c716cfebe182e"
  },
  "v2ray_cartel": {
    "last_updated": "2025-08-07T01:10:13.356198",
    "file_hash": "3339dcd7c8fa4479896173d68deaf3f7"
  },
  "v2ray_string": {
    "last_updated": "2025-08-06T18:22:58.666536",
    "file_hash": "cb1e4f7589e91fbff355a9323ea3b942"
  },
  "v2rayi_net": {
    "last_updated": "2025-08-07T06:24:45.975540",
    "file_hash": "7bb3a26d1d569803423594cf515d9536"
  },
  "v2rayprotocol": {
    "last_updated": "2025-08-07T12:31:42.787834",
    "file_hash": "e23d173a017e12f548f2369ed121a36a"
  },
  "v2rayy_vpn13": {
    "last_updated": "2025-08-14T20:27:17.949126",
    "file_hash": "95cc5dc17a11a2224f2c50c8d0af2dcd"
  },
  "vipv2rey": {
    "last_updated": "2025-08-07T12:31:42.787834",
    "file_hash": "35f52aa45557bd0249da0add9a4eb643"
  },
  "vmessprotocol": {
    "last_updated": "2025-08-07T12:31:42.787834",
    "file_hash": "edab8042933959faa2c6a70a654af2f6"
  },
  "vpn_315": {
    "last_updated": "2025-08-07T06:24:45.975540",
    "file_hash": "9fe3a228323f1936dabb6b7620e476b0"
  },
  "vpngate_config": {
    "last_updated": "2025-08-07T12:31:42.787834",
    "file_hash": "f22ba54c7a38027726820f429c051a09"
  },
  "vpnhouse_official": {
    "last_updated": "2025-08-07T12:31:42.787834",
    "file_hash": "9e00ee0696f4b4f40fc7cf83a2f0ccfa"
  },
  "vpnserverrr": {
    "last_updated": "2025-08-07T12:31:42.787834",
    "file_hash": "8fb12b730cf0072113025f185bd58334"
  },
  "vpnvg": {
    "last_updated": "2025-08-07T01:10:13.356198",
    "file_hash": "afdefc0ab78fdbd9ad1710707b92329d"
  },
  "womanlifefreedom13": {
    "last_updated": "2025-08-05T18:24:27.926148",
    "file_hash": "b2fb85d3b1b76addb950a95bd635ca24"
  },
  "anix_v2ray": {
    "last_updated": "2025-08-06T18:22:58.666536",
    "file_hash": "2e6d7334de4c36285b275ddbbce3adb8"
  },
  "astrovpn_official": {
    "last_updated": "2025-08-07T06:24:45.975540",
    "file_hash": "1dd3022412c8d4890d9418b5933cab0f"
  },
  "bestvpn4030": {
    "last_updated": "2025-08-07T12:31:42.787834",
    "file_hash": "85467adf1ea52d246aa8a65508975e55"
  },
  "cav2ray": {
    "last_updated": "2025-08-06T01:09:59.624461",
    "file_hash": "917b22efb3241be079b8a786f0dee582"
  },
  "ch_a2l": {
    "last_updated": "2025-08-07T12:31:42.787834",
    "file_hash": "3fca88287cf60684fda77610fb9aa39b"
  },
  "easy_free_vpn": {
    "last_updated": "2025-08-07T18:23:48.248052",
    "file_hash": "da1f3cf3b808a167902b08791d3ff421"
  },
  "freevpnhomesconfigs": {
    "last_updated": "2025-08-07T01:10:13.356198",
    "file_hash": "afad278a21e6a5945c9d077e2f3d0509"
  },
  "goldd_v2ray": {
    "last_updated": "2025-08-04T07:04:02.194800",
    "file_hash": "8f873e4b32b03f217daf2e6b56f93286"
  },
  "khalaa_vpn": {
    "last_updated": "2025-08-14T20:27:17.949126",
    "file_hash": "697613cadc689505bad7a87bde21cc2b"
  },
  "m_vipv2ray": {
    "last_updated": "2025-08-14T20:27:17.949126",
    "file_hash": "a7ae6ab94f2e2d11918fb7812d1d730b"
  },
  "mr_vpn123": {
    "last_updated": "2025-08-06T18:22:58.666536",
    "file_hash": "8829d2a6794922868132fcb82b46690f"
  },
  "nofilter_v2rayng": {
    "last_updated": "2025-08-14T20:27:17.949126",
    "file_hash": "2afd744fd76a3714a8c7f1930b6ec87a"
  },
  "parsashonam": {
    "last_updated": "2025-08-05T12:31:44.499348",
    "file_hash": "5298957aec58ace8732e97697ebbc414"
  },
  "persian_proxy6": {
    "last_updated": "2025-08-07T12:31:42.787834",
    "file_hash": "3da1c5b7fb60d766d5c15f68ba821168"
  },
  "phiilshekn": {
    "last_updated": "2025-08-07T01:10:13.356198",
    "file_hash": "ecb60a91264228a479cfa858468c90e4"
  },
  "rez1vpn": {
    "last_updated": "2025-08-07T01:10:13.356198",
    "file_hash": "9bdae1ec3a029369ab087e6079599acb"
  },
  "server444": {
    "last_updated": "2025-08-07T06:24:45.975540",
    "file_hash": "4337b5bf5c55ff44bc8ac9a567f7935b"
  },
  "serverv2ray00": {
    "last_updated": "2025-08-07T06:24:45.975540",
    "file_hash": "72f5cafc4a1fe6e3ce32a1ad88d3ab88"
  },
  "seven_ping": {
    "last_updated": "2025-08-14T20:27:17.949126",
    "file_hash": "e2f7be6443cead24761f5352c99f4f90"
  },
  "shadowsocksshop": {
    "last_updated": "2025-08-07T12:31:42.787834",
    "file_hash": "5432f11acfeaa69bf72ea98233bb92ad"
  },
  "superpinghub": {
    "last_updated": "2025-08-05T18:24:27.926148",
    "file_hash": "c42f54ec46e0f4c7a63ff50d1ea1ac9e"
  },
  "torang_vpn": {
    "last_updated": "2025-08-07T06:24:45.975540",
    "file_hash": "790e4041dc427fb79d9bbfdff3a8d38a"
  },
  "unlimiteddev": {
    "last_updated": "2025-08-07T18:23:48.248052",
    "file_hash": "9766c77229b7cdf3aaa4448b69d36c16"
  },
  "v2ra2": {
    "last_updated": "2025-08-07T12:31:42.787834",
    "file_hash": "157a7981ea985983b05ddca50c1f1065"
  },
  "v2raayngconfig": {
    "last_updated": "2025-08-07T06:24:45.975540",
    "file_hash": "3f40e1bf8dc77f4edc664018b7a479de"
  },
  "v2ray009": {
    "last_updated": "2025-08-07T18:23:48.248052",
    "file_hash": "91c8f0e57730158db9601df537fd2e7c"
  },
  "v2ray313": {
    "last_updated": "2025-08-07T12:31:42.787834",
    "file_hash": "a8b21e41077fcf12934315765286b124"
  },
  "v2ray_for_free": {
    "last_updated": "2025-08-07T01:10:13.356198",
    "file_hash": "a036080a2382f73b5e06c56b841f66fb"
  },
  "v2ray_god": {
    "last_updated": "2025-08-07T06:24:45.975540",
    "file_hash": "bf637a44c9370934f204b9eb68dd88cb"
  },
  "v2ray_vpnalfa": {
    "last_updated": "2025-08-06T06:25:33.942702",
    "file_hash": "c9f38383d3f93e5506d1fd6195773cd1"
  },
  "v2raybe": {
    "last_updated": "2025-08-07T06:24:45.975540",
    "file_hash": "d30edf0d2c8f348b7be114c8a59c6291"
  },
  "v2rayfree": {
    "last_updated": "2025-08-14T09:02:42.969926",
    "file_hash": "e67941db18d2c93b4541e58031dacf52"
  },
  "v2rayng_channel_vpn": {
    "last_updated": "2025-08-07T01:10:13.356198",
    "file_hash": "e9a8a0b7d1cf2dc6f258430777ec5332"
  },
  "v2rayngvpn_1": {
    "last_updated": "2025-08-14T20:27:17.949126",
    "file_hash": "f51cb7fa37f9f58235173724c77fec77"
  },
  "vipnetmeli": {
    "last_updated": "2025-08-07T18:23:48.248052",
    "file_hash": "f0550f5b9421a9a4acec4eb7b4c67e09"
  },
  "vipvpn_v2ray": {
    "last_updated": "2025-08-14T20:27:17.949126",
    "file_hash": "2735e3121994b02e60d7df8cb7fdde76"
  },
  "vpn_arta": {
    "last_updated": "2025-08-07T12:31:42.787834",
    "file_hash": "4674e1f2bc52549440953bd57405fe75"
  },
  "vpn_room": {
    "last_updated": "2025-08-14T20:27:17.949126",
    "file_hash": "9eaf53b22a8bf932aadf2a104ae0fabc"
  },
  "vpnepic": {
    "last_updated": "2025-08-07T06:24:45.975540",
    "file_hash": "9cf04d19fdfdffb85bbf3479c2d08ce0"
  },
  "vpnpacket": {
    "last_updated": "2025-08-04T07:04:02.194800",
    "file_hash": "c660576f9770e666ae99f6fa3f28322e"
  },
  "vpntrt": {
    "last_updated": "2025-08-07T01:10:13.356198",
    "file_hash": "e98e1bf19c59defe1c4155e550ee5c75"
  },
  "wancloudfa": {
    "last_updated": "2025-08-07T18:23:48.248052",
    "file_hash": "02a1a1fd15479c1e4969cc042b8ec6ee"
  },
  "wbrovers": {
    "last_updated": "2025-08-06T18:22:58.666536",
    "file_hash": "78e53df1bf62f053068fb6eb470477c7"
  },
  "xivpn": {
    "last_updated": "2025-08-07T01:10:13.356198",
    "file_hash": "e2b53235d5dbc24d970bedda35b54b5e"
  },
  "nufilter": {
    "last_updated": "2025-08-07T12:31:42.787834",
    "file_hash": "34dfc04a79d4ed7ad33fbcae4a3060ec"
  },
  "WPSNET": {
    "last_updated": "2025-08-07T01:10:13.356198",
    "file_hash": "e129521b638b5d2c6adfda107be22208"
  },
  "flyv2ray": {
    "last_updated": "2025-08-07T18:23:48.248052",
    "file_hash": "47bff92f4ae08ec4e63cadf5f7d1c0dc"
  },
  "SafeNet_Server": {
    "last_updated": "2025-08-06T06:25:33.942702",
    "file_hash": "7dd75917d55c02c7cdd9541bf299a7a4"
  },
  "EuServer": {
    "last_updated": "2025-08-07T06:24:45.975540",
    "file_hash": "6f657a3c8238f91b44c2b755d3dcf61f"
  },
  "fnet00": {
    "last_updated": "2025-08-07T06:24:45.975540",
    "file_hash": "34504a00e53392ce79d06174d62a2323"
  },
  "JiedianSsr": {
    "last_updated": "2025-08-07T18:23:48.248052",
    "file_hash": "1410f8a01fc6318238ef3f0b5535e10a"
  },
  "alismartvpn": {
    "last_updated": "2025-08-07T06:24:45.975540",
    "file_hash": "948516c78611fe4586561a6b2244a7b2"
  },
  "argooo_vpn": {
    "last_updated": "2025-08-06T01:09:59.624461",
    "file_hash": "b91bd5e6c36df8de8c60ecad7348ad85"
  },
  "armod_iran": {
    "last_updated": "2025-08-14T20:27:17.949126",
    "file_hash": "d1f1e5fd657b0e54c070287e1f30e414"
  },
  "catvpns": {
    "last_updated": "2025-08-07T12:31:42.787834",
    "file_hash": "659a7a77ef60aba429f9d5945b98a08b"
  },
  "configpluse": {
    "last_updated": "2025-08-14T20:27:17.949126",
    "file_hash": "528734333ace9d0dc726e66af3d1a34f"
  },
  "configv2rayforfree": {
    "last_updated": "2025-08-07T06:24:45.975540",
    "file_hash": "dcdfb8060ba38cac8caab343317bfb48"
  },
  "ehsawn8": {
    "last_updated": "2025-08-07T12:31:42.787834",
    "file_hash": "9aa4f09950b37cadd13b5438425880e9"
  },
  "freakconfig": {
    "last_updated": "2025-08-07T18:23:48.248052",
    "file_hash": "afcd5cca6864abb499f907b8512d45a6"
  },
  "hajimamadvpn": {
    "last_updated": "2025-08-07T01:10:13.356198",
    "file_hash": "0fb810e1065cfdb1ef79f76fb8ff859c"
  },
  "novavpn1984": {
    "last_updated": "2025-08-07T01:10:13.356198",
    "file_hash": "9f3fb6bb2d02b30aa21e0fb068364707"
  },
  "pak4you": {
    "last_updated": "2025-08-07T18:23:48.248052",
    "file_hash": "3314ef17c7629f0f34cd1fd7c2fe4445"
  },
  "ppal03": {
    "last_updated": "2025-08-07T01:10:13.356198",
    "file_hash": "1cdcf833a04d6813a785614439f2afc5"
  },
  "qeshmserver": {
    "last_updated": "2025-08-07T12:31:42.787834",
    "file_hash": "ab5034b38250b65c58772ed13ab4152b"
  },
  "servernett": {
    "last_updated": "2025-08-10T09:10:59.220452",
    "file_hash": "2c202bb3014cbc8339b1c96cdb38f2e4"
  },
  "share_nodes": {
    "last_updated": "2025-08-07T06:24:45.975540",
    "file_hash": "8ae5d214d32dc342a43b99e2a141ffb1"
  },
  "v2fetch": {
    "last_updated": "2025-08-07T12:31:42.787834",
    "file_hash": "469581d8007d3254f680e658ba75e066"
  },
  "v2ray03": {
    "last_updated": "2025-08-07T01:10:13.356198",
    "file_hash": "db5e2c1962687e3a7bd5e93ef2dba9e4"
  },
  "v2ray_rolly": {
    "last_updated": "2025-08-07T06:24:45.975540",
    "file_hash": "b323319890fa5ba17bff45028d57f370"
  },
  "v2rayfree1": {
    "last_updated": "2025-08-07T18:23:48.248052",
    "file_hash": "24ee39648267f8c7dbd476b7f6bfc5e0"
  },
  "v2rayngninja": {
    "last_updated": "2025-08-07T06:24:45.975540",
    "file_hash": "afb164a08ba7d64f0ab2a47fe1674143"
  },
  "v2rayngseven": {
    "last_updated": "2025-08-14T20:27:17.949126",
    "file_hash": "3d98458197b48b2371d2c54a1fd2a590"
  },
  "v2rayvpn2": {
    "last_updated": "2025-08-06T12:31:31.275312",
    "file_hash": "73745e9c690385111bbac258c270c68e"
  },
  "vipufovpn": {
    "last_updated": "2025-08-07T01:10:13.356198",
    "file_hash": "e28114a1b7bb115febd8a90ab6dff1eb"
  },
  "vmesskhodam": {
    "last_updated": "2025-08-07T06:24:45.975540",
    "file_hash": "295bd052f7a6da24cdcff103a6d92aea"
  },
  "vpnfastservice": {
    "last_updated": "2025-08-07T12:31:42.787834",
    "file_hash": "ef0dbaee5c1726f9c923b5a21f7bdbdb"
  },
  "vpnplusee_free": {
    "last_updated": "2025-08-07T12:31:42.787834",
    "file_hash": "34a2fadbe8b2f0decaa4b50f5c508738"
  },
  "vtworay_wolf": {
    "last_updated": "2025-08-06T01:09:59.624461",
    "file_hash": "171b1c216af9da33de8c3abf9eac050c"
  },
  "zibanabz": {
    "last_updated": "2025-08-07T12:31:42.787834",
    "file_hash": "89df640e1a290f244bd390558ef71637"
  },
  "antifilterservice": {
    "last_updated": "2025-08-07T01:10:13.356198",
    "file_hash": "46e841be221e2d69cf7cde7811c3118f"
  },
  "buffalo_vpn": {
    "last_updated": "2025-08-07T01:10:13.356198",
    "file_hash": "07ed39e190ae36e878a6f0368d8dbee3"
  },
  "eliv2ray": {
    "last_updated": "2025-08-07T06:24:45.975540",
    "file_hash": "64e5c092a3ee26c1d1ee4fa94c7cef00"
  },
  "fasst_vpn": {
    "last_updated": "2025-08-07T06:24:45.975540",
    "file_hash": "9a3630742ac2ba0f7518c7a6e133f1b7"
  },
  "fire_vpn_channel": {
    "last_updated": "2025-08-07T12:31:42.787834",
    "file_hash": "8c812711f2a0220ed15a93f25c7106fe"
  },
  "golestan_vpn": {
    "last_updated": "2025-08-07T01:10:13.356198",
    "file_hash": "a3aa3c6c1acc1e84f6d1b8a8b7dfc8dc"
  },
  "golf_vpn": {
    "last_updated": "2025-08-07T18:23:48.248052",
    "file_hash": "c0433e95b69dbf50397f538873c81988"
  },
  "iran_v2ray1": {
    "last_updated": "2025-08-07T12:31:42.787834",
    "file_hash": "56c346b5380724fe02c2b6fea030e6e2"
  },
  "jiedianssr": {
    "last_updated": "2025-08-07T12:31:42.787834",
    "file_hash": "0bf6ffad45b3d6ef2064863f323aa718"
  },
  "jokerv2ray": {
    "last_updated": "2025-08-07T18:23:48.248052",
    "file_hash": "3f4786ba3c90228efec5ac7eeadb8e63"
  },
  "kingoclubs": {
    "last_updated": "2025-08-07T12:31:42.787834",
    "file_hash": "e3e2982d77ac88405c1c7dcd53956262"
  },
  "kurdistan_vpn_perfectt": {
    "last_updated": "2025-08-07T06:24:45.975540",
    "file_hash": "94330cc62e70560ecd8714fcea810dba"
  },
  "lakvpn1": {
    "last_updated": "2025-08-07T01:10:13.356198",
    "file_hash": "ccfa50588c0919727cdec1034bb77754"
  },
  "mdvpnsec": {
    "last_updated": "2025-08-07T06:24:45.975540",
    "file_hash": "ff954418062ea2fc41528705c8a97994"
  },
  "my_proxii": {
    "last_updated": "2025-08-05T18:24:27.926148",
    "file_hash": "aa139b2c8b822e0d23ef285bbd0bbcc7"
  },
  "ntconfig": {
    "last_updated": "2025-08-07T18:23:48.248052",
    "file_hash": "ca5c1e67bc6a295ac81bed07e87f383a"
  },
  "privatevpns": {
    "last_updated": "2025-08-07T01:10:13.356198",
    "file_hash": "67fa3023cfa7494cb2e96ca0d5cfcfb5"
  },
  "proxy48": {
    "last_updated": "2025-08-14T20:27:17.949126",
    "file_hash": "e317494114bda6ef5f9ce266d1af6838"
  },
  "public504": {
    "last_updated": "2025-08-06T18:22:58.666536",
    "file_hash": "f17338bcd09cbdbff40fbc97316d0065"
  },
  "rayanconf": {
    "last_updated": "2025-08-07T06:24:45.975540",
    "file_hash": "36d423bcca4611926eeccf789e9e00f3"
  },
  "server_nekobox": {
    "last_updated": "2025-08-07T18:23:48.248052",
    "file_hash": "075564bd3bdf9841e076f18a40b42e0d"
  },
  "toyota_proxyyyy": {
    "last_updated": "2025-08-07T12:31:42.787834",
    "file_hash": "efe39829366143fe8ead2923e2d08e69"
  },
  "v2mod": {
    "last_updated": "2025-08-07T18:23:48.248052",
    "file_hash": "602aec6ca71c25b39433fe4756e55dd9"
  },
  "v2ray4free": {
    "last_updated": "2025-08-07T18:23:48.248052",
    "file_hash": "35157558003594210df087c016336138"
  },
  "v2raycactus": {
    "last_updated": "2025-08-07T18:23:48.248052",
    "file_hash": "0be4de7e5fc696fe329d2d3ea630b4ed"
  },
  "v2raydiyako": {
    "last_updated": "2025-08-07T06:24:45.975540",
    "file_hash": "8fc615f3bbfe603e9a1652ebb8c26033"
  },
  "v2rayland02": {
    "last_updated": "2025-08-14T20:27:17.949126",
    "file_hash": "2b8fadb7a58d777803f5e33532a13c6c"
  },
  "v2rayng_fast": {
    "last_updated": "2025-08-04T12:31:40.411501",
    "file_hash": "f6e4868ffa54701461abd2a3895a834b"
  },
  "v2rayngconfiig": {
    "last_updated": "2025-08-07T01:10:13.356198",
    "file_hash": "5b728395d0e1d3c2e8b60203101975dc"
  },
  "v2rayvpnclub": {
    "last_updated": "2025-08-07T18:23:48.248052",
    "file_hash": "c429ac599dec581a3b78003e7f1c4ffb"
  },
  "v2ry_proxy": {
    "last_updated": "2025-08-07T18:23:48.248052",
    "file_hash": "80eda6648cfc7a984fc3366eb511ac3e"
  },
  "vpidiamond": {
    "last_updated": "2025-08-07T01:10:13.356198",
    "file_hash": "62e3e968b7e2533a3e76572f71352160"
  },
  "vpn_bal0uch": {
    "last_updated": "2025-08-07T01:10:13.356198",
    "file_hash": "a0ff955b090899a5fb7f484cbf44228a"
  },
  "vpn_wedbaz2": {
    "last_updated": "2025-08-07T06:24:45.975540",
    "file_hash": "3aa112184a23cb2bb9a156a55d92dfd8"
  },
  "vpncostumer": {
    "last_updated": "2025-08-14T20:27:17.949126",
    "file_hash": "3629a9d1eb665736b69ac1b10d8d54f2"
  },
  "vpnwlf": {
    "last_updated": "2025-08-07T01:10:13.356198",
    "file_hash": "73d42086d7756c00c6efb46fbd1aa371"
  },
  "yasv2ray": {
    "last_updated": "2025-08-07T06:24:45.975540",
    "file_hash": "cb32dca93d3b877ca9aee765065946b0"
  },
  "freeownvpn": {
    "last_updated": "2025-08-07T06:24:45.975540",
    "file_hash": "24f45411b22f99be98e9109916d14001"
  },
  "vpn_Nv1": {
    "last_updated": "2025-08-07T06:24:45.975540",
    "file_hash": "6b3f3f2a5fecf53cceb084f831ffda44"
  },
  "customv2ray": {
    "last_updated": "2025-08-07T18:23:48.248052",
    "file_hash": "8fdfc87fd0df34f7711f48a1e58c4665"
  },
  "Outlinev2rayNG": {
    "last_updated": "2025-08-07T12:31:42.787834",
    "file_hash": "e06c9b920be57431fad276576eab846f"
  },
  "V2rayng_Fast": {
    "last_updated": "2025-08-04T18:22:59.976494",
    "file_hash": "e4431a99ca5df4d9b91c7db715c5574e"
  },
  "DigiV2ray": {
    "last_updated": "2025-08-07T18:23:48.248052",
    "file_hash": "bf5a653bd241fb9f9d96eb8b6afc34fe"
  },
  "Baraye_azadi_Info": {
    "last_updated": "2025-08-07T06:24:45.975540",
    "file_hash": "3843aa4de943f17108d0b5830fe75ed7"
  },
  "academi_vpn": {
    "last_updated": "2025-08-07T12:31:42.787834",
    "file_hash": "d4ab84601c8db4a34c6b461c85505ed2"
  },
  "angus_vpn3": {
    "last_updated": "2025-08-07T06:24:45.975540",
    "file_hash": "6578caefa908a82c05890526401fa04b"
  },
  "caa_v2ray": {
    "last_updated": "2025-08-07T12:31:42.787834",
    "file_hash": "ce3ab0ecefd7439c914041823196d3b0"
  },
  "freeconfing": {
    "last_updated": "2025-08-07T06:24:45.975540",
    "file_hash": "eb5f109f31bc4ba03295a39b067c45eb"
  },
  "freenetpro99": {
    "last_updated": "2025-08-07T06:24:45.975540",
    "file_hash": "9ad140381b8d6cbe08c71afd28659e3f"
  },
  "freevlessvpn": {
    "last_updated": "2025-08-07T18:23:48.248052",
    "file_hash": "9dbf9dc0c6e44204f9037a460594817a"
  },
  "grizzlyvpn": {
    "last_updated": "2025-08-06T06:25:33.942702",
    "file_hash": "e682e84ea8bed236bcd0fcde3fef0ab8"
  },
  "iranmedicalvpn": {
    "last_updated": "2025-08-14T20:27:17.949126",
    "file_hash": "80deaf09d54e70ff2a234954c7ab3788"
  },
  "jcvpn": {
    "last_updated": "2025-08-07T18:23:48.248052",
    "file_hash": "5d97724cb2a9f1380859e784327e9a57"
  },
  "kesslervpn": {
    "last_updated": "2025-08-07T06:24:45.975540",
    "file_hash": "f20ea0182ffcc37a6e4e8344f7a4f876"
  },
  "moft_vpn": {
    "last_updated": "2025-08-09T02:18:08.966063",
    "file_hash": "2510f77a3279019b532a07f07e843658"
  },
  "mtpv2ray": {
    "last_updated": "2025-08-07T12:31:42.787834",
    "file_hash": "2b19bde8f72739fa8fcc5290671b7f62"
  },
  "nim_vpn_ir": {
    "last_updated": "2025-08-07T18:23:48.248052",
    "file_hash": "648ed98105a209f8d096692c98521ba2"
  },
  "nitrovpne": {
    "last_updated": "2025-08-07T06:24:45.975540",
    "file_hash": "585f47ea6a42f49ba7e5155c892419d9"
  },
  "proxysudo": {
    "last_updated": "2025-08-06T12:31:31.275312",
    "file_hash": "e4a78db2d696084de9c52f09769e6b4e"
  },
  "radiofarex": {
    "last_updated": "2025-08-07T12:31:42.787834",
    "file_hash": "e8fba9906ae27007ffeb3e3a4e3bbd0c"
  },
  "speedconfig00": {
    "last_updated": "2025-08-07T06:24:45.975540",
    "file_hash": "5716e3de0c98883d27825993c7a5301f"
  },
  "v2boxng74": {
    "last_updated": "2025-08-07T18:23:48.248052",
    "file_hash": "e55095d70a57fd649e2594c198aeaa9f"
  },
  "v2mystery": {
    "last_updated": "2025-08-06T18:22:58.666536",
    "file_hash": "e249a7a6a862c549a3f60ce1fdaa2536"
  },
  "v2ray_configs_pool": {
    "last_updated": "2025-08-04T18:22:59.976494",
    "file_hash": "22f4deb873987c83f57dcc625f5b5d51"
  },
  "v2ray_vmes": {
    "last_updated": "2025-08-07T06:24:45.975540",
    "file_hash": "d6d54247db86fd8e04153409c979f82c"
  },
  "v2raytg": {
    "last_updated": "2025-08-14T20:27:17.949126",
    "file_hash": "70d91063a2f2eee15dec281b7b10c301"
  },
  "v2rayvpn009": {
    "last_updated": "2025-08-07T12:31:42.787834",
    "file_hash": "80979f4d56a81caf7f817352eae4e9c7"
  },
  "v_2ray1": {
    "last_updated": "2025-08-07T12:31:42.787834",
    "file_hash": "1fdb7465c9178f5c3ef150dced92218b"
  },
  "vipv2rayngnp": {
    "last_updated": "2025-08-07T06:24:45.975540",
    "file_hash": "cc41737d3d9f4fa1fa6ae8d714bdf66f"
  },
  "vpn4ir_1": {
    "last_updated": "2025-08-14T20:27:17.949126",
    "file_hash": "1442356a5bc9e6b00a2cd0b38298ab01"
  },
  "vpnplus100": {
    "last_updated": "2025-08-07T12:31:42.787834",
    "file_hash": "62b9b96b5696b7bcb8417249566f2469"
  },
  "vpnserver_tel": {
    "last_updated": "2025-08-07T18:23:48.248052",
    "file_hash": "b3fd1ebbd9ab6be0f150f52e0b26c4a5"
  },
  "x4azadi": {
    "last_updated": "2025-08-14T20:27:17.949126",
    "file_hash": "2a625fad450e53c4d65461771b92c7ad"
  },
  "xnxv2ray": {
    "last_updated": "2025-08-07T18:23:48.248052",
    "file_hash": "9b295ebd6423ebfae06bc6d7ea8236d2"
  },
  "yuproxytelegram": {
    "last_updated": "2025-08-14T20:27:17.949126",
    "file_hash": "a637114c29b705f3c35e89a5513cdce6"
  },
  "zedmodeonvpn": {
    "last_updated": "2025-08-07T18:23:48.248052",
    "file_hash": "f2bdee2083428ddb13505f13e43c4137"
  },
  "zvpnn": {
    "last_updated": "2025-08-07T06:24:45.975540",
    "file_hash": "087b9d093361ff173e32ac8b1a3e0184"
  },
  "blueberrynetwork": {
    "last_updated": "2025-08-07T12:31:42.787834",
    "file_hash": "c8090cd8a1dc84173235c95df872056c"
  },
  "bpjzx2": {
    "last_updated": "2025-08-06T18:22:58.666536",
    "file_hash": "87e80c79e21e96d936d38a8c0dd3039a"
  },
  "euserver": {
    "last_updated": "2025-08-07T06:24:45.975540",
    "file_hash": "6f657a3c8238f91b44c2b755d3dcf61f"
  },
  "hennessypro": {
    "last_updated": "2025-08-07T06:24:45.975540",
    "file_hash": "a8c282f6a9664995d0b9087657038a37"
  },
  "igrsdet": {
    "last_updated": "2025-08-14T20:27:17.949126",
    "file_hash": "f59943c0f29000c4bdc1196628ce7a77"
  },
  "internet_nor": {
    "last_updated": "2025-08-07T06:24:45.975540",
    "file_hash": "b0f88bcdd08fc5ae772c6b12fa7ffb3b"
  },
  "iranbaxvpn": {
    "last_updated": "2025-08-14T20:27:17.949126",
    "file_hash": "02a3738223e072bf07cab55e8a7b22c3"
  },
  "maxshare": {
    "last_updated": "2025-08-14T20:27:17.949126",
    "file_hash": "927b8cbfc40a14e4007cf377a5cb614a"
  },
  "mimitdl": {
    "last_updated": "2025-08-07T12:31:42.787834",
    "file_hash": "6120205f414ce94061c581dffb90d6bc"
  },
  "piavpngo": {
    "last_updated": "2025-08-07T06:24:45.975540",
    "file_hash": "194928578274657a0d81505490ff3689"
  },
  "proxy_mtproto_vpns_free": {
    "last_updated": "2025-08-14T09:02:42.969926",
    "file_hash": "e67941db18d2c93b4541e58031dacf52"
  },
  "selinc": {
    "last_updated": "2025-08-07T18:23:48.248052",
    "file_hash": "9027ca9c7da2530c3ef8e8288a55291c"
  },
  "trand_farsi": {
    "last_updated": "2025-08-06T01:09:59.624461",
    "file_hash": "b16123021d06c7921f7f5a2adb4c967a"
  },
  "v2ray_raha": {
    "last_updated": "2025-08-07T06:24:45.975540",
    "file_hash": "7a85b855acba39934a0a7418afbe7418"
  },
  "v2rayng_lion": {
    "last_updated": "2025-08-07T12:31:42.787834",
    "file_hash": "6e6ae1b52bfa9eff20544910ab48de08"
  },
  "vpn_gold_free_1": {
    "last_updated": "2025-08-06T12:31:31.275312",
    "file_hash": "e7360e1c39575137be5b15f59b353bc4"
  },
  "vpnpopular2023": {
    "last_updated": "2025-08-07T12:31:42.787834",
    "file_hash": "4a2c6109ed415a5f6596dd5d7cb1bf40"
  },
  "v2pedia": {
    "last_updated": "2025-08-14T20:27:17.949126",
    "file_hash": "201856c09b856434d0917468992f9f64"
  },
  "vless_vmess": {
    "last_updated": "2025-08-07T06:24:45.975540",
    "file_hash": "8930133c20f1de9826d20bd690e88fb3"
  },
  "DeamNet_proxy": {
    "last_updated": "2025-08-07T12:31:42.787834",
    "file_hash": "b542fbb06070d20af8a30907dbb5c0e5"
  },
  "WomanLifeFreedomVPN": {
    "last_updated": "2025-08-14T14:20:13.719500",
    "file_hash": "29dd7725e1a26f36cca8fc90284a5320"
  },
  "amirinventor2010": {
    "last_updated": "2025-08-14T20:27:17.949126",
    "file_hash": "93de86756614a51cc2c2c2f8f6e6fed2"
  },
  "bluevpn_v2ray": {
    "last_updated": "2025-08-14T20:27:17.949126",
    "file_hash": "33cc0428f5628697d59190936032c981"
  },
  "realvpnmaster": {
    "last_updated": "2025-08-07T18:23:48.248052",
    "file_hash": "28a51b849d05dd0cfefcb52d8ed4ccb9"
  },
  "serversiran11": {
    "last_updated": "2025-08-07T01:10:13.356198",
    "file_hash": "b11fc0f4c8345ba5fbffd95ffda05b77"
  },
  "v2rayng_ribvar": {
    "last_updated": "2025-08-07T18:23:48.248052",
    "file_hash": "93718c45e7c7d474599d411839269c2c"
  },
  "v2rayvmess": {
    "last_updated": "2025-08-06T12:31:31.275312",
    "file_hash": "e00e0aa0ea56feeb6ea531cf7c61254e"
  },
  "v2ryng01": {
    "last_updated": "2025-08-14T20:27:17.949126",
    "file_hash": "637b0749da97ffb7397f0ceaff39a955"
  },
  "vpncostume": {
    "last_updated": "2025-08-14T20:27:17.949126",
    "file_hash": "ccb026405f98aeebf06b70f286e93d55"
  },
  "vpnfreeaccounts": {
    "last_updated": "2025-08-06T18:22:58.666536",
    "file_hash": "2895b126c87bb1254f8897da13933bb9"
  },
  "iran_access": {
    "last_updated": "2025-08-14T20:27:17.949126",
    "file_hash": "c0f41439c40e6835274122387c884ea0"
  },
  "mt_team_iran": {
    "last_updated": "2025-08-14T20:27:17.949126",
    "file_hash": "560dfa99e52c44d13b2d9c4f0a04c614"
  },
  "v2raxx": {
    "last_updated": "2025-08-14T20:27:17.949126",
    "file_hash": "0d7b891521206d655bd9632043d416c8"
  },
  "v2rayngvvpn": {
    "last_updated": "2025-08-07T12:31:42.787834",
    "file_hash": "ef35e634ad7e379f5be7f8fa2762c784"
  },
  "webshecan": {
    "last_updated": "2025-08-07T12:31:42.787834",
    "file_hash": "655bfe457227f445177b510fb731ff84"
  },
  "Hope_Net": {
    "last_updated": "2025-08-06T18:22:58.666536",
    "file_hash": "a55a8262651c3707f88dc348ab5756f1"
  },
  "mehrosaboran": {
    "last_updated": "2025-08-06T18:22:58.666536",
    "file_hash": "176aa63754ca9161c40cc44f5fe18c11"
  },
  "rxv2ray": {
    "last_updated": "2025-08-07T18:23:48.248052",
    "file_hash": "edaa98f33a1168118acc107822ffe422"
  },
  "bored_vpn": {
    "last_updated": "2025-08-14T20:27:17.949126",
    "file_hash": "359d56c728a2c4c5a1d1085ad767f34a"
  },
  "cpuvpn": {
    "last_updated": "2025-08-06T12:31:31.275312",
    "file_hash": "9111f2d812e83cc73215f9d53f1d46e8"
  },
  "disvpn": {
    "last_updated": "2025-08-14T20:27:17.949126",
    "file_hash": "a1d6d00ce75953a911e917e813a545c2"
  },
  "falcunargo": {
    "last_updated": "2025-08-06T12:31:31.275312",
    "file_hash": "496df505a755dbfa732b112c00c31c74"
  },
  "v2raycrow": {
    "last_updated": "2025-08-07T18:23:48.248052",
    "file_hash": "27a0d19789f6f7bc2376cef2d8bd033b"
  },
  "v2rayngconfings": {
    "last_updated": "2025-08-14T20:27:17.949126",
    "file_hash": "7e8966274a83b8e2d65665f6fc04c1d2"
  },
  "v2_r_ayng": {
    "last_updated": "2025-08-07T18:23:48.248052",
    "file_hash": "4e67dbcd1a9367152ab9f8321e0ad3fc"
  },
  "antifilterjadid3": {
    "last_updated": "2025-08-06T18:22:58.666536",
    "file_hash": "b0c9b23e36986ec1a3936882897d8627"
  },
  "deragv2ray": {
    "last_updated": "2025-08-07T01:10:13.356198",
    "file_hash": "408a26414018f6059f279794c0a8c126"
  },
  "vlessconfig": {
    "last_updated": "2025-08-07T06:24:45.975540",
    "file_hash": "93de28c63ccb5dda1d94efb97d2f449f"
  },
  "Vpn_Tehran": {
    "last_updated": "2025-08-07T01:10:13.356198",
    "file_hash": "5d5db8a08c59b0759a6dd2cb15a59247"
  },
  "betv2ray": {
    "last_updated": "2025-08-05T18:24:27.926148",
    "file_hash": "2093a78382746cbde1608fd4cf060a87"
  },
  "vpn_tehran": {
    "last_updated": "2025-08-07T01:10:13.356198",
    "file_hash": "5d5db8a08c59b0759a6dd2cb15a59247"
  },
  "vistav2ray": {
    "last_updated": "2025-08-07T12:31:42.787834",
    "file_hash": "9259331646d043c345b04a840f118495"
  },
  "configt": {
    "last_updated": "2025-08-06T06:25:33.942702",
    "file_hash": "e93ba948507299e382862cc4d6118dbe"
  },
  "DarkTeam_VPN": {
    "last_updated": "2025-08-07T18:23:48.248052",
    "file_hash": "f631fe6254014d4b435cb1a320e8649b"
  },
  "svnteam": {
    "last_updated": "2025-08-14T20:27:17.949126",
    "file_hash": "83b24956c2f8600fafae825c8a15c650"
  },
  "dingyue_Center": {
    "last_updated": "2025-08-07T12:31:42.787834",
    "file_hash": "d91db400441d2096cf39b734ca5dc6bd"
  },
  "payam_nsi": {
    "last_updated": "2025-08-14T20:27:17.949126",
    "file_hash": "5b32f34a97a6a59785f9e56d71d5b61d"
  }
}